[{"seq":"0","name":"AirThreatInfo_ToComm","id":"65","owner":"ATSManager","date":"20251103","time":"23:32:06.946","elapsed_time":"805","instance_id":"0","alignment":"false","omt":"false","type":"interaction","operation":"send","data":{"Header.MessageID":{"values":["65"]},"Header.MessageLength":{"values":["0"]},"AirThreatInfo.ObjectID":{"values":["0"]},"AirThreatInfo.ObjectState":{"values":["0"]},"AirThreatInfo.PositionX":{"values":["0.00000000"]},"AirThreatInfo.PositionY":{"values":["0.00000000"]},"AirThreatInfo.VelocityX":{"values":["0.00000000"]},"AirThreatInfo.VelocityY":{"values":["0.00000000"]}},"length":"40","serialized":"00410000000000000000000000000000000000000000000000000000000000000000000000000000"},{"seq":"1","name":"AirThreatInfo_ToComm","id":"65","owner":"ATSManager","date":"20251103","time":"23:32:07.445","elapsed_time":"1304","instance_id":"0","alignment":"false","omt":"false","type":"interaction","operation":"send","data":{"Header.MessageID":{"values":["65"]},"Header.MessageLength":{"values":["0"]},"AirThreatInfo.ObjectID":{"values":["0"]},"AirThreatInfo.ObjectState":{"values":["0"]},"AirThreatInfo.PositionX":{"values":["0.00000000"]},"AirThreatInfo.PositionY":{"values":["0.00000000"]},"AirThreatInfo.VelocityX":{"values":["0.00000000"]},"AirThreatInfo.VelocityY":{"values":["0.00000000"]}},"length":"40","serialized":"00410000000000000000000000000000000000000000000000000000000000000000000000000000"},{"seq":"2","name":"SimulatorStateToComm","id":"32","owner":"StateManager","date":"20251103","time":"23:32:07.514","elapsed_time":"1373","instance_id":"0","alignment":"false","omt":"false","type":"interaction","operation":"send","data":{"SimulatorID":{"values":["102"]}},"length":"2","serialized":"0066"},{"seq":"3","name":"AirThreatInfo_ToComm","id":"65","owner":"ATSManager","date":"20251103","time":"23:32:07.945","elapsed_time":"1804","instance_id":"0","alignment":"false","omt":"false","type":"interaction","operation":"send","data":{"Header.MessageID":{"values":["65"]},"Header.MessageLength":{"values":["0"]},"AirThreatInfo.ObjectID":{"values":["0"]},"AirThreatInfo.ObjectState":{"values":["0"]},"AirThreatInfo.PositionX":{"values":["0.00000000"]},"AirThreatInfo.PositionY":{"values":["0.00000000"]},"AirThreatInfo.VelocityX":{"values":["0.00000000"]},"AirThreatInfo.VelocityY":{"values":["0.00000000"]}},"length":"40","serialized":"00410000000000000000000000000000000000000000000000000000000000000000000000000000"},{"seq":"4","name":"AirThreatInfo_ToComm","id":"65","owner":"ATSManager","date":"20251103","time":"23:32:08.446","elapsed_time":"2305","instance_id":"0","alignment":"false","omt":"false","type":"interaction","operation":"send","data":{"Header.MessageID":{"values":["65"]},"Header.MessageLength":{"values":["0"]},"AirThreatInfo.ObjectID":{"values":["0"]},"AirThreatInfo.ObjectState":{"values":["0"]},"AirThreatInfo.PositionX":{"values":["0.00000000"]},"AirThreatInfo.PositionY":{"values":["0.00000000"]},"AirThreatInfo.VelocityX":{"values":["0.00000000"]},"AirThreatInfo.VelocityY":{"values":["0.00000000"]}},"length":"40","serialized":"00410000000000000000000000000000000000000000000000000000000000000000000000000000"},{"seq":"5","name":"SimulatorStateToComm","id":"32","owner":"StateManager","date":"20251103","time":"23:32:08.514","elapsed_time":"2373","instance_id":"0","alignment":"false","omt":"false","type":"interaction","operation":"send","data":{"SimulatorID":{"values":["102"]}},"length":"2","serialized":"0066"},{"seq":"6","name":"AirThreatInfo_ToComm","id":"65","owner":"ATSManager","date":"20251103","time":"23:32:08.945","elapsed_time":"2804","instance_id":"0","alignment":"false","omt":"false","type":"interaction","operation":"send","data":{"Header.MessageID":{"values":["65"]},"Header.MessageLength":{"values":["0"]},"AirThreatInfo.ObjectID":{"values":["0"]},"AirThreatInfo.ObjectState":{"values":["0"]},"AirThreatInfo.PositionX":{"values":["0.00000000"]},"AirThreatInfo.PositionY":{"values":["0.00000000"]},"AirThreatInfo.VelocityX":{"values":["0.00000000"]},"AirThreatInfo.VelocityY":{"values":["0.00000000"]}},"length":"40","serialized":"00410000000000000000000000000000000000000000000000000000000000000000000000000000"},{"seq":"7","name":"AirThreatInfo_ToComm","id":"65","owner":"ATSManager","date":"20251103","time":"23:32:09.446","elapsed_time":"3305","instance_id":"0","alignment":"false","omt":"false","type":"interaction","operation":"send","data":{"Header.MessageID":{"values":["65"]},"Header.MessageLength":{"values":["0"]},"AirThreatInfo.ObjectID":{"values":["0"]},"AirThreatInfo.ObjectState":{"values":["0"]},"AirThreatInfo.PositionX":{"values":["0.00000000"]},"AirThreatInfo.PositionY":{"values":["0.00000000"]},"AirThreatInfo.VelocityX":{"values":["0.00000000"]},"AirThreatInfo.VelocityY":{"values":["0.00000000"]}},"length":"40","serialized":"00410000000000000000000000000000000000000000000000000000000000000000000000000000"},{"seq":"8","name":"SimulatorStateToComm","id":"32","owner":"StateManager","date":"20251103","time":"23:32:09.514","elapsed_time":"3373","instance_id":"0","alignment":"false","omt":"false","type":"interaction","operation":"send","data":{"SimulatorID":{"values":["102"]}},"length":"2","serialized":"0066"},{"seq":"9","name":"AirThreatInfo_ToComm","id":"65","owner":"ATSManager","date":"20251103","time":"23:32:09.945","elapsed_time":"3804","instance_id":"0","alignment":"false","omt":"false","type":"interaction","operation":"send","data":{"Header.MessageID":{"values":["65"]},"Header.MessageLength":{"values":["0"]},"AirThreatInfo.ObjectID":{"values":["0"]},"AirThreatInfo.ObjectState":{"values":["0"]},"AirThreatInfo.PositionX":{"values":["0.00000000"]},"AirThreatInfo.PositionY":{"values":["0.00000000"]},"AirThreatInfo.VelocityX":{"values":["0.00000000"]},"AirThreatInfo.VelocityY":{"values":["0.00000000"]}},"length":"40","serialized":"00410000000000000000000000000000000000000000000000000000000000000000000000000000"},{"seq":"10","name":"AirThreatInfo_ToComm","id":"65","owner":"ATSManager","date":"20251103","time":"23:32:10.445","elapsed_time":"4304","instance_id":"0","alignment":"false","omt":"false","type":"interaction","operation":"send","data":{"Header.MessageID":{"values":["65"]},"Header.MessageLength":{"values":["0"]},"AirThreatInfo.ObjectID":{"values":["0"]},"AirThreatInfo.ObjectState":{"values":["0"]},"AirThreatInfo.PositionX":{"values":["0.00000000"]},"AirThreatInfo.PositionY":{"values":["0.00000000"]},"AirThreatInfo.VelocityX":{"values":["0.00000000"]},"AirThreatInfo.VelocityY":{"values":["0.00000000"]}},"length":"40","serialized":"00410000000000000000000000000000000000000000000000000000000000000000000000000000"},{"seq":"11","name":"SimulatorStateToComm","id":"32","owner":"StateManager","date":"20251103","time":"23:32:10.513","elapsed_time":"4372","instance_id":"0","alignment":"false","omt":"false","type":"interaction","operation":"send","data":{"SimulatorID":{"values":["102"]}},"length":"2","serialized":"0066"},{"seq":"12","name":"AirThreatInfo_ToComm","id":"65","owner":"ATSManager","date":"20251103","time":"23:32:10.946","elapsed_time":"4805","instance_id":"0","alignment":"false","omt":"false","type":"interaction","operation":"send","data":{"Header.MessageID":{"values":["65"]},"Header.MessageLength":{"values":["0"]},"AirThreatInfo.ObjectID":{"values":["0"]},"AirThreatInfo.ObjectState":{"values":["0"]},"AirThreatInfo.PositionX":{"values":["0.00000000"]},"AirThreatInfo.PositionY":{"values":["0.00000000"]},"AirThreatInfo.VelocityX":{"values":["0.00000000"]},"AirThreatInfo.VelocityY":{"values":["0.00000000"]}},"length":"40","serialized":"00410000000000000000000000000000000000000000000000000000000000000000000000000000"},{"seq":"13","name":"AirThreatInfo_ToComm","id":"65","owner":"ATSManager","date":"20251103","time":"23:32:11.446","elapsed_time":"5305","instance_id":"0","alignment":"false","omt":"false","type":"interaction","operation":"send","data":{"Header.MessageID":{"values":["65"]},"Header.MessageLength":{"values":["0"]},"AirThreatInfo.ObjectID":{"values":["0"]},"AirThreatInfo.ObjectState":{"values":["0"]},"AirThreatInfo.PositionX":{"values":["0.00000000"]},"AirThreatInfo.PositionY":{"values":["0.00000000"]},"AirThreatInfo.VelocityX":{"values":["0.00000000"]},"AirThreatInfo.VelocityY":{"values":["0.00000000"]}},"length":"40","serialized":"00410000000000000000000000000000000000000000000000000000000000000000000000000000"},{"seq":"14","name":"SimulatorStateToComm","id":"32","owner":"StateManager","date":"20251103","time":"23:32:11.514","elapsed_time":"5373","instance_id":"0","alignment":"false","omt":"false","type":"interaction","operation":"send","data":{"SimulatorID":{"values":["102"]}},"length":"2","serialized":"0066"},{"seq":"15","name":"AirThreatInfo_ToComm","id":"65","owner":"ATSManager","date":"20251103","time":"23:32:11.945","elapsed_time":"5804","instance_id":"0","alignment":"false","omt":"false","type":"interaction","operation":"send","data":{"Header.MessageID":{"values":["65"]},"Header.MessageLength":{"values":["0"]},"AirThreatInfo.ObjectID":{"values":["0"]},"AirThreatInfo.ObjectState":{"values":["0"]},"AirThreatInfo.PositionX":{"values":["0.00000000"]},"AirThreatInfo.PositionY":{"values":["0.00000000"]},"AirThreatInfo.VelocityX":{"values":["0.00000000"]},"AirThreatInfo.VelocityY":{"values":["0.00000000"]}},"length":"40","serialized":"00410000000000000000000000000000000000000000000000000000000000000000000000000000"},{"seq":"16","name":"AirThreatInfo_ToComm","id":"65","owner":"ATSManager","date":"20251103","time":"23:32:12.446","elapsed_time":"6305","instance_id":"0","alignment":"false","omt":"false","type":"interaction","operation":"send","data":{"Header.MessageID":{"values":["65"]},"Header.MessageLength":{"values":["0"]},"AirThreatInfo.ObjectID":{"values":["0"]},"AirThreatInfo.ObjectState":{"values":["0"]},"AirThreatInfo.PositionX":{"values":["0.00000000"]},"AirThreatInfo.PositionY":{"values":["0.00000000"]},"AirThreatInfo.VelocityX":{"values":["0.00000000"]},"AirThreatInfo.VelocityY":{"values":["0.00000000"]}},"length":"40","serialized":"00410000000000000000000000000000000000000000000000000000000000000000000000000000"},{"seq":"17","name":"SimulatorStateToComm","id":"32","owner":"StateManager","date":"20251103","time":"23:32:12.514","elapsed_time":"6373","instance_id":"0","alignment":"false","omt":"false","type":"interaction","operation":"send","data":{"SimulatorID":{"values":["102"]}},"length":"2","serialized":"0066"},{"seq":"18","name":"AirThreatInfo_ToComm","id":"65","owner":"ATSManager","date":"20251103","time":"23:32:12.946","elapsed_time":"6805","instance_id":"0","alignment":"false","omt":"false","type":"interaction","operation":"send","data":{"Header.MessageID":{"values":["65"]},"Header.MessageLength":{"values":["0"]},"AirThreatInfo.ObjectID":{"values":["0"]},"AirThreatInfo.ObjectState":{"values":["0"]},"AirThreatInfo.PositionX":{"values":["0.00000000"]},"AirThreatInfo.PositionY":{"values":["0.00000000"]},"AirThreatInfo.VelocityX":{"values":["0.00000000"]},"AirThreatInfo.VelocityY":{"values":["0.00000000"]}},"length":"40","serialized":"00410000000000000000000000000000000000000000000000000000000000000000000000000000"},{"seq":"19","name":"AirThreatInfo_ToComm","id":"65","owner":"ATSManager","date":"20251103","time":"23:32:13.445","elapsed_time":"7304","instance_id":"0","alignment":"false","omt":"false","type":"interaction","operation":"send","data":{"Header.MessageID":{"values":["65"]},"Header.MessageLength":{"values":["0"]},"AirThreatInfo.ObjectID":{"values":["0"]},"AirThreatInfo.ObjectState":{"values":["0"]},"AirThreatInfo.PositionX":{"values":["0.00000000"]},"AirThreatInfo.PositionY":{"values":["0.00000000"]},"AirThreatInfo.VelocityX":{"values":["0.00000000"]},"AirThreatInfo.VelocityY":{"values":["0.00000000"]}},"length":"40","serialized":"00410000000000000000000000000000000000000000000000000000000000000000000000000000"},{"seq":"20","name":"SimulatorStateToComm","id":"32","owner":"StateManager","date":"20251103","time":"23:32:13.513","elapsed_time":"7372","instance_id":"0","alignment":"false","omt":"false","type":"interaction","operation":"send","data":{"SimulatorID":{"values":["102"]}},"length":"2","serialized":"0066"},{"seq":"21","name":"AirThreatInfo_ToComm","id":"65","owner":"ATSManager","date":"20251103","time":"23:32:13.945","elapsed_time":"7804","instance_id":"0","alignment":"false","omt":"false","type":"interaction","operation":"send","data":{"Header.MessageID":{"values":["65"]},"Header.MessageLength":{"values":["0"]},"AirThreatInfo.ObjectID":{"values":["0"]},"AirThreatInfo.ObjectState":{"values":["0"]},"AirThreatInfo.PositionX":{"values":["0.00000000"]},"AirThreatInfo.PositionY":{"values":["0.00000000"]},"AirThreatInfo.VelocityX":{"values":["0.00000000"]},"AirThreatInfo.VelocityY":{"values":["0.00000000"]}},"length":"40","serialized":"00410000000000000000000000000000000000000000000000000000000000000000000000000000"},{"seq":"22","name":"AirThreatInfo_ToComm","id":"65","owner":"ATSManager","date":"20251103","time":"23:32:14.446","elapsed_time":"8305","instance_id":"0","alignment":"false","omt":"false","type":"interaction","operation":"send","data":{"Header.MessageID":{"values":["65"]},"Header.MessageLength":{"values":["0"]},"AirThreatInfo.ObjectID":{"values":["0"]},"AirThreatInfo.ObjectState":{"values":["0"]},"AirThreatInfo.PositionX":{"values":["0.00000000"]},"AirThreatInfo.PositionY":{"values":["0.00000000"]},"AirThreatInfo.VelocityX":{"values":["0.00000000"]},"AirThreatInfo.VelocityY":{"values":["0.00000000"]}},"length":"40","serialized":"00410000000000000000000000000000000000000000000000000000000000000000000000000000"},{"seq":"23","name":"SimulatorStateToComm","id":"32","owner":"StateManager","date":"20251103","time":"23:32:14.514","elapsed_time":"8373","instance_id":"0","alignment":"false","omt":"false","type":"interaction","operation":"send","data":{"SimulatorID":{"values":["102"]}},"length":"2","serialized":"0066"},{"seq":"24","name":"AirThreatInfo_ToComm","id":"65","owner":"ATSManager","date":"20251103","time":"23:32:14.944","elapsed_time":"8803","instance_id":"0","alignment":"false","omt":"false","type":"interaction","operation":"send","data":{"Header.MessageID":{"values":["65"]},"Header.MessageLength":{"values":["0"]},"AirThreatInfo.ObjectID":{"values":["0"]},"AirThreatInfo.ObjectState":{"values":["0"]},"AirThreatInfo.PositionX":{"values":["0.00000000"]},"AirThreatInfo.PositionY":{"values":["0.00000000"]},"AirThreatInfo.VelocityX":{"values":["0.00000000"]},"AirThreatInfo.VelocityY":{"values":["0.00000000"]}},"length":"40","serialized":"00410000000000000000000000000000000000000000000000000000000000000000000000000000"},{"seq":"25","name":"AirThreatInfo_ToComm","id":"65","owner":"ATSManager","date":"20251103","time":"23:32:15.445","elapsed_time":"9304","instance_id":"0","alignment":"false","omt":"false","type":"interaction","operation":"send","data":{"Header.MessageID":{"values":["65"]},"Header.MessageLength":{"values":["0"]},"AirThreatInfo.ObjectID":{"values":["0"]},"AirThreatInfo.ObjectState":{"values":["0"]},"AirThreatInfo.PositionX":{"values":["0.00000000"]},"AirThreatInfo.PositionY":{"values":["0.00000000"]},"AirThreatInfo.VelocityX":{"values":["0.00000000"]},"AirThreatInfo.VelocityY":{"values":["0.00000000"]}},"length":"40","serialized":"00410000000000000000000000000000000000000000000000000000000000000000000000000000"},{"seq":"26","name":"SimulatorStateToComm","id":"32","owner":"StateManager","date":"20251103","time":"23:32:15.514","elapsed_time":"9373","instance_id":"0","alignment":"false","omt":"false","type":"interaction","operation":"send","data":{"SimulatorID":{"values":["102"]}},"length":"2","serialized":"0066"},{"seq":"27","name":"AirThreatInfo_ToComm","id":"65","owner":"ATSManager","date":"20251103","time":"23:32:15.946","elapsed_time":"9805","instance_id":"0","alignment":"false","omt":"false","type":"interaction","operation":"send","data":{"Header.MessageID":{"values":["65"]},"Header.MessageLength":{"values":["0"]},"AirThreatInfo.ObjectID":{"values":["0"]},"AirThreatInfo.ObjectState":{"values":["0"]},"AirThreatInfo.PositionX":{"values":["0.00000000"]},"AirThreatInfo.PositionY":{"values":["0.00000000"]},"AirThreatInfo.VelocityX":{"values":["0.00000000"]},"AirThreatInfo.VelocityY":{"values":["0.00000000"]}},"length":"40","serialized":"00410000000000000000000000000000000000000000000000000000000000000000000000000000"},{"seq":"28","name":"AirThreatInfo_ToComm","id":"65","owner":"ATSManager","date":"20251103","time":"23:32:16.445","elapsed_time":"10304","instance_id":"0","alignment":"false","omt":"false","type":"interaction","operation":"send","data":{"Header.MessageID":{"values":["65"]},"Header.MessageLength":{"values":["0"]},"AirThreatInfo.ObjectID":{"values":["0"]},"AirThreatInfo.ObjectState":{"values":["0"]},"AirThreatInfo.PositionX":{"values":["0.00000000"]},"AirThreatInfo.PositionY":{"values":["0.00000000"]},"AirThreatInfo.VelocityX":{"values":["0.00000000"]},"AirThreatInfo.VelocityY":{"values":["0.00000000"]}},"length":"40","serialized":"00410000000000000000000000000000000000000000000000000000000000000000000000000000"},{"seq":"29","name":"SimulatorStateToComm","id":"32","owner":"StateManager","date":"20251103","time":"23:32:16.513","elapsed_time":"10372","instance_id":"0","alignment":"false","omt":"false","type":"interaction","operation":"send","data":{"SimulatorID":{"values":["102"]}},"length":"2","serialized":"0066"},{"seq":"30","name":"AirThreatInfo_ToComm","id":"65","owner":"ATSManager","date":"20251103","time":"23:32:16.946","elapsed_time":"10805","instance_id":"0","alignment":"false","omt":"false","type":"interaction","operation":"send","data":{"Header.MessageID":{"values":["65"]},"Header.MessageLength":{"values":["0"]},"AirThreatInfo.ObjectID":{"values":["0"]},"AirThreatInfo.ObjectState":{"values":["0"]},"AirThreatInfo.PositionX":{"values":["0.00000000"]},"AirThreatInfo.PositionY":{"values":["0.00000000"]},"AirThreatInfo.VelocityX":{"values":["0.00000000"]},"AirThreatInfo.VelocityY":{"values":["0.00000000"]}},"length":"40","serialized":"00410000000000000000000000000000000000000000000000000000000000000000000000000000"},{"seq":"31","name":"AirThreatInfo_ToComm","id":"65","owner":"ATSManager","date":"20251103","time":"23:32:17.446","elapsed_time":"11305","instance_id":"0","alignment":"false","omt":"false","type":"interaction","operation":"send","data":{"Header.MessageID":{"values":["65"]},"Header.MessageLength":{"values":["0"]},"AirThreatInfo.ObjectID":{"values":["0"]},"AirThreatInfo.ObjectState":{"values":["0"]},"AirThreatInfo.PositionX":{"values":["0.00000000"]},"AirThreatInfo.PositionY":{"values":["0.00000000"]},"AirThreatInfo.VelocityX":{"values":["0.00000000"]},"AirThreatInfo.VelocityY":{"values":["0.00000000"]}},"length":"40","serialized":"00410000000000000000000000000000000000000000000000000000000000000000000000000000"},{"seq":"32","name":"SimulatorStateToComm","id":"32","owner":"StateManager","date":"20251103","time":"23:32:17.514","elapsed_time":"11373","instance_id":"0","alignment":"false","omt":"false","type":"interaction","operation":"send","data":{"SimulatorID":{"values":["102"]}},"length":"2","serialized":"0066"},{"seq":"33","name":"AirThreatInfo_ToComm","id":"65","owner":"ATSManager","date":"20251103","time":"23:32:17.945","elapsed_time":"11804","instance_id":"0","alignment":"false","omt":"false","type":"interaction","operation":"send","data":{"Header.MessageID":{"values":["65"]},"Header.MessageLength":{"values":["0"]},"AirThreatInfo.ObjectID":{"values":["0"]},"AirThreatInfo.ObjectState":{"values":["0"]},"AirThreatInfo.PositionX":{"values":["0.00000000"]},"AirThreatInfo.PositionY":{"values":["0.00000000"]},"AirThreatInfo.VelocityX":{"values":["0.00000000"]},"AirThreatInfo.VelocityY":{"values":["0.00000000"]}},"length":"40","serialized":"00410000000000000000000000000000000000000000000000000000000000000000000000000000"},{"seq":"34","name":"AirThreatInfo_ToComm","id":"65","owner":"ATSManager","date":"20251103","time":"23:32:18.446","elapsed_time":"12305","instance_id":"0","alignment":"false","omt":"false","type":"interaction","operation":"send","data":{"Header.MessageID":{"values":["65"]},"Header.MessageLength":{"values":["0"]},"AirThreatInfo.ObjectID":{"values":["0"]},"AirThreatInfo.ObjectState":{"values":["0"]},"AirThreatInfo.PositionX":{"values":["0.00000000"]},"AirThreatInfo.PositionY":{"values":["0.00000000"]},"AirThreatInfo.VelocityX":{"values":["0.00000000"]},"AirThreatInfo.VelocityY":{"values":["0.00000000"]}},"length":"40","serialized":"00410000000000000000000000000000000000000000000000000000000000000000000000000000"},{"seq":"35","name":"SimulatorStateToComm","id":"32","owner":"StateManager","date":"20251103","time":"23:32:18.514","elapsed_time":"12373","instance_id":"0","alignment":"false","omt":"false","type":"interaction","operation":"send","data":{"SimulatorID":{"values":["102"]}},"length":"2","serialized":"0066"},{"seq":"36","name":"AirThreatInfo_ToComm","id":"65","owner":"ATSManager","date":"20251103","time":"23:32:18.945","elapsed_time":"12804","instance_id":"0","alignment":"false","omt":"false","type":"interaction","operation":"send","data":{"Header.MessageID":{"values":["65"]},"Header.MessageLength":{"values":["0"]},"AirThreatInfo.ObjectID":{"values":["0"]},"AirThreatInfo.ObjectState":{"values":["0"]},"AirThreatInfo.PositionX":{"values":["0.00000000"]},"AirThreatInfo.PositionY":{"values":["0.00000000"]},"AirThreatInfo.VelocityX":{"values":["0.00000000"]},"AirThreatInfo.VelocityY":{"values":["0.00000000"]}},"length":"40","serialized":"00410000000000000000000000000000000000000000000000000000000000000000000000000000"},{"seq":"37","name":"AirThreatInfo_ToComm","id":"65","owner":"ATSManager","date":"20251103","time":"23:32:19.444","elapsed_time":"13303","instance_id":"0","alignment":"false","omt":"false","type":"interaction","operation":"send","data":{"Header.MessageID":{"values":["65"]},"Header.MessageLength":{"values":["0"]},"AirThreatInfo.ObjectID":{"values":["0"]},"AirThreatInfo.ObjectState":{"values":["0"]},"AirThreatInfo.PositionX":{"values":["0.00000000"]},"AirThreatInfo.PositionY":{"values":["0.00000000"]},"AirThreatInfo.VelocityX":{"values":["0.00000000"]},"AirThreatInfo.VelocityY":{"values":["0.00000000"]}},"length":"40","serialized":"00410000000000000000000000000000000000000000000000000000000000000000000000000000"},{"seq":"38","name":"SimulatorStateToComm","id":"32","owner":"StateManager","date":"20251103","time":"23:32:19.513","elapsed_time":"13372","instance_id":"0","alignment":"false","omt":"false","type":"interaction","operation":"send","data":{"SimulatorID":{"values":["102"]}},"length":"2","serialized":"0066"},{"seq":"39","name":"AirThreatInfo_ToComm","id":"65","owner":"ATSManager","date":"20251103","time":"23:32:19.946","elapsed_time":"13805","instance_id":"0","alignment":"false","omt":"false","type":"interaction","operation":"send","data":{"Header.MessageID":{"values":["65"]},"Header.MessageLength":{"values":["0"]},"AirThreatInfo.ObjectID":{"values":["0"]},"AirThreatInfo.ObjectState":{"values":["0"]},"AirThreatInfo.PositionX":{"values":["0.00000000"]},"AirThreatInfo.PositionY":{"values":["0.00000000"]},"AirThreatInfo.VelocityX":{"values":["0.00000000"]},"AirThreatInfo.VelocityY":{"values":["0.00000000"]}},"length":"40","serialized":"00410000000000000000000000000000000000000000000000000000000000000000000000000000"},{"seq":"40","name":"AirThreatInfo_ToComm","id":"65","owner":"ATSManager","date":"20251103","time":"23:32:20.446","elapsed_time":"14305","instance_id":"0","alignment":"false","omt":"false","type":"interaction","operation":"send","data":{"Header.MessageID":{"values":["65"]},"Header.MessageLength":{"values":["0"]},"AirThreatInfo.ObjectID":{"values":["0"]},"AirThreatInfo.ObjectState":{"values":["0"]},"AirThreatInfo.PositionX":{"values":["0.00000000"]},"AirThreatInfo.PositionY":{"values":["0.00000000"]},"AirThreatInfo.VelocityX":{"values":["0.00000000"]},"AirThreatInfo.VelocityY":{"values":["0.00000000"]}},"length":"40","serialized":"00410000000000000000000000000000000000000000000000000000000000000000000000000000"},{"seq":"41","name":"SimulatorStateToComm","id":"32","owner":"StateManager","date":"20251103","time":"23:32:20.513","elapsed_time":"14372","instance_id":"0","alignment":"false","omt":"false","type":"interaction","operation":"send","data":{"SimulatorID":{"values":["102"]}},"length":"2","serialized":"0066"},{"seq":"42","name":"AirThreatInfo_ToComm","id":"65","owner":"ATSManager","date":"20251103","time":"23:32:20.946","elapsed_time":"14805","instance_id":"0","alignment":"false","omt":"false","type":"interaction","operation":"send","data":{"Header.MessageID":{"values":["65"]},"Header.MessageLength":{"values":["0"]},"AirThreatInfo.ObjectID":{"values":["0"]},"AirThreatInfo.ObjectState":{"values":["0"]},"AirThreatInfo.PositionX":{"values":["0.00000000"]},"AirThreatInfo.PositionY":{"values":["0.00000000"]},"AirThreatInfo.VelocityX":{"values":["0.00000000"]},"AirThreatInfo.VelocityY":{"values":["0.00000000"]}},"length":"40","serialized":"00410000000000000000000000000000000000000000000000000000000000000000000000000000"},{"seq":"43","name":"AirThreatInfo_ToComm","id":"65","owner":"ATSManager","date":"20251103","time":"23:32:21.445","elapsed_time":"15304","instance_id":"0","alignment":"false","omt":"false","type":"interaction","operation":"send","data":{"Header.MessageID":{"values":["65"]},"Header.MessageLength":{"values":["0"]},"AirThreatInfo.ObjectID":{"values":["0"]},"AirThreatInfo.ObjectState":{"values":["0"]},"AirThreatInfo.PositionX":{"values":["0.00000000"]},"AirThreatInfo.PositionY":{"values":["0.00000000"]},"AirThreatInfo.VelocityX":{"values":["0.00000000"]},"AirThreatInfo.VelocityY":{"values":["0.00000000"]}},"length":"40","serialized":"00410000000000000000000000000000000000000000000000000000000000000000000000000000"},{"seq":"44","name":"SimulatorStateToComm","id":"32","owner":"StateManager","date":"20251103","time":"23:32:21.513","elapsed_time":"15372","instance_id":"0","alignment":"false","omt":"false","type":"interaction","operation":"send","data":{"SimulatorID":{"values":["102"]}},"length":"2","serialized":"0066"},{"seq":"45","name":"AirThreatInfo_ToComm","id":"65","owner":"ATSManager","date":"20251103","time":"23:32:21.945","elapsed_time":"15804","instance_id":"0","alignment":"false","omt":"false","type":"interaction","operation":"send","data":{"Header.MessageID":{"values":["65"]},"Header.MessageLength":{"values":["0"]},"AirThreatInfo.ObjectID":{"values":["0"]},"AirThreatInfo.ObjectState":{"values":["0"]},"AirThreatInfo.PositionX":{"values":["0.00000000"]},"AirThreatInfo.PositionY":{"values":["0.00000000"]},"AirThreatInfo.VelocityX":{"values":["0.00000000"]},"AirThreatInfo.VelocityY":{"values":["0.00000000"]}},"length":"40","serialized":"00410000000000000000000000000000000000000000000000000000000000000000000000000000"},{"seq":"46","name":"AirThreatInfo_ToComm","id":"65","owner":"ATSManager","date":"20251103","time":"23:32:22.445","elapsed_time":"16304","instance_id":"0","alignment":"false","omt":"false","type":"interaction","operation":"send","data":{"Header.MessageID":{"values":["65"]},"Header.MessageLength":{"values":["0"]},"AirThreatInfo.ObjectID":{"values":["0"]},"AirThreatInfo.ObjectState":{"values":["0"]},"AirThreatInfo.PositionX":{"values":["0.00000000"]},"AirThreatInfo.PositionY":{"values":["0.00000000"]},"AirThreatInfo.VelocityX":{"values":["0.00000000"]},"AirThreatInfo.VelocityY":{"values":["0.00000000"]}},"length":"40","serialized":"00410000000000000000000000000000000000000000000000000000000000000000000000000000"},{"seq":"47","name":"SimulatorStateToComm","id":"32","owner":"StateManager","date":"20251103","time":"23:32:22.513","elapsed_time":"16372","instance_id":"0","alignment":"false","omt":"false","type":"interaction","operation":"send","data":{"SimulatorID":{"values":["102"]}},"length":"2","serialized":"0066"},{"seq":"48","name":"AirThreatInfo_ToComm","id":"65","owner":"ATSManager","date":"20251103","time":"23:32:22.945","elapsed_time":"16804","instance_id":"0","alignment":"false","omt":"false","type":"interaction","operation":"send","data":{"Header.MessageID":{"values":["65"]},"Header.MessageLength":{"values":["0"]},"AirThreatInfo.ObjectID":{"values":["0"]},"AirThreatInfo.ObjectState":{"values":["0"]},"AirThreatInfo.PositionX":{"values":["0.00000000"]},"AirThreatInfo.PositionY":{"values":["0.00000000"]},"AirThreatInfo.VelocityX":{"values":["0.00000000"]},"AirThreatInfo.VelocityY":{"values":["0.00000000"]}},"length":"40","serialized":"00410000000000000000000000000000000000000000000000000000000000000000000000000000"},{"seq":"49","name":"AirThreatInfo_ToComm","id":"65","owner":"ATSManager","date":"20251103","time":"23:32:23.445","elapsed_time":"17304","instance_id":"0","alignment":"false","omt":"false","type":"interaction","operation":"send","data":{"Header.MessageID":{"values":["65"]},"Header.MessageLength":{"values":["0"]},"AirThreatInfo.ObjectID":{"values":["0"]},"AirThreatInfo.ObjectState":{"values":["0"]},"AirThreatInfo.PositionX":{"values":["0.00000000"]},"AirThreatInfo.PositionY":{"values":["0.00000000"]},"AirThreatInfo.VelocityX":{"values":["0.00000000"]},"AirThreatInfo.VelocityY":{"values":["0.00000000"]}},"length":"40","serialized":"00410000000000000000000000000000000000000000000000000000000000000000000000000000"},{"seq":"50","name":"SimulatorStateToComm","id":"32","owner":"StateManager","date":"20251103","time":"23:32:23.514","elapsed_time":"17373","instance_id":"0","alignment":"false","omt":"false","type":"interaction","operation":"send","data":{"SimulatorID":{"values":["102"]}},"length":"2","serialized":"0066"},{"seq":"51","name":"AirThreatInfo_ToComm","id":"65","owner":"ATSManager","date":"20251103","time":"23:32:23.945","elapsed_time":"17804","instance_id":"0","alignment":"false","omt":"false","type":"interaction","operation":"send","data":{"Header.MessageID":{"values":["65"]},"Header.MessageLength":{"values":["0"]},"AirThreatInfo.ObjectID":{"values":["0"]},"AirThreatInfo.ObjectState":{"values":["0"]},"AirThreatInfo.PositionX":{"values":["0.00000000"]},"AirThreatInfo.PositionY":{"values":["0.00000000"]},"AirThreatInfo.VelocityX":{"values":["0.00000000"]},"AirThreatInfo.VelocityY":{"values":["0.00000000"]}},"length":"40","serialized":"00410000000000000000000000000000000000000000000000000000000000000000000000000000"},{"seq":"52","name":"AirThreatInfo_ToComm","id":"65","owner":"ATSManager","date":"20251103","time":"23:32:24.445","elapsed_time":"18304","instance_id":"0","alignment":"false","omt":"false","type":"interaction","operation":"send","data":{"Header.MessageID":{"values":["65"]},"Header.MessageLength":{"values":["0"]},"AirThreatInfo.ObjectID":{"values":["0"]},"AirThreatInfo.ObjectState":{"values":["0"]},"AirThreatInfo.PositionX":{"values":["0.00000000"]},"AirThreatInfo.PositionY":{"values":["0.00000000"]},"AirThreatInfo.VelocityX":{"values":["0.00000000"]},"AirThreatInfo.VelocityY":{"values":["0.00000000"]}},"length":"40","serialized":"00410000000000000000000000000000000000000000000000000000000000000000000000000000"},{"seq":"53","name":"SimulatorStateToComm","id":"32","owner":"StateManager","date":"20251103","time":"23:32:24.514","elapsed_time":"18373","instance_id":"0","alignment":"false","omt":"false","type":"interaction","operation":"send","data":{"SimulatorID":{"values":["102"]}},"length":"2","serialized":"0066"},{"seq":"54","name":"AirThreatInfo_ToComm","id":"65","owner":"ATSManager","date":"20251103","time":"23:32:24.946","elapsed_time":"18805","instance_id":"0","alignment":"false","omt":"false","type":"interaction","operation":"send","data":{"Header.MessageID":{"values":["65"]},"Header.MessageLength":{"values":["0"]},"AirThreatInfo.ObjectID":{"values":["0"]},"AirThreatInfo.ObjectState":{"values":["0"]},"AirThreatInfo.PositionX":{"values":["0.00000000"]},"AirThreatInfo.PositionY":{"values":["0.00000000"]},"AirThreatInfo.VelocityX":{"values":["0.00000000"]},"AirThreatInfo.VelocityY":{"values":["0.00000000"]}},"length":"40","serialized":"00410000000000000000000000000000000000000000000000000000000000000000000000000000"},{"seq":"55","name":"AirThreatInfo_ToComm","id":"65","owner":"ATSManager","date":"20251103","time":"23:32:25.445","elapsed_time":"19304","instance_id":"0","alignment":"false","omt":"false","type":"interaction","operation":"send","data":{"Header.MessageID":{"values":["65"]},"Header.MessageLength":{"values":["0"]},"AirThreatInfo.ObjectID":{"values":["0"]},"AirThreatInfo.ObjectState":{"values":["0"]},"AirThreatInfo.PositionX":{"values":["0.00000000"]},"AirThreatInfo.PositionY":{"values":["0.00000000"]},"AirThreatInfo.VelocityX":{"values":["0.00000000"]},"AirThreatInfo.VelocityY":{"values":["0.00000000"]}},"length":"40","serialized":"00410000000000000000000000000000000000000000000000000000000000000000000000000000"},{"seq":"56","name":"SimulatorStateToComm","id":"32","owner":"StateManager","date":"20251103","time":"23:32:25.513","elapsed_time":"19372","instance_id":"0","alignment":"false","omt":"false","type":"interaction","operation":"send","data":{"SimulatorID":{"values":["102"]}},"length":"2","serialized":"0066"},{"seq":"57","name":"AirThreatInfo_ToComm","id":"65","owner":"ATSManager","date":"20251103","time":"23:32:25.944","elapsed_time":"19803","instance_id":"0","alignment":"false","omt":"false","type":"interaction","operation":"send","data":{"Header.MessageID":{"values":["65"]},"Header.MessageLength":{"values":["0"]},"AirThreatInfo.ObjectID":{"values":["0"]},"AirThreatInfo.ObjectState":{"values":["0"]},"AirThreatInfo.PositionX":{"values":["0.00000000"]},"AirThreatInfo.PositionY":{"values":["0.00000000"]},"AirThreatInfo.VelocityX":{"values":["0.00000000"]},"AirThreatInfo.VelocityY":{"values":["0.00000000"]}},"length":"40","serialized":"00410000000000000000000000000000000000000000000000000000000000000000000000000000"},{"seq":"58","name":"AirThreatInfo_ToComm","id":"65","owner":"ATSManager","date":"20251103","time":"23:32:26.445","elapsed_time":"20304","instance_id":"0","alignment":"false","omt":"false","type":"interaction","operation":"send","data":{"Header.MessageID":{"values":["65"]},"Header.MessageLength":{"values":["0"]},"AirThreatInfo.ObjectID":{"values":["0"]},"AirThreatInfo.ObjectState":{"values":["0"]},"AirThreatInfo.PositionX":{"values":["0.00000000"]},"AirThreatInfo.PositionY":{"values":["0.00000000"]},"AirThreatInfo.VelocityX":{"values":["0.00000000"]},"AirThreatInfo.VelocityY":{"values":["0.00000000"]}},"length":"40","serialized":"00410000000000000000000000000000000000000000000000000000000000000000000000000000"},{"seq":"59","name":"SimulatorStateToComm","id":"32","owner":"StateManager","date":"20251103","time":"23:32:26.513","elapsed_time":"20372","instance_id":"0","alignment":"false","omt":"false","type":"interaction","operation":"send","data":{"SimulatorID":{"values":["102"]}},"length":"2","serialized":"0066"},{"seq":"60","name":"AirThreatInfo_ToComm","id":"65","owner":"ATSManager","date":"20251103","time":"23:32:26.946","elapsed_time":"20805","instance_id":"0","alignment":"false","omt":"false","type":"interaction","operation":"send","data":{"Header.MessageID":{"values":["65"]},"Header.MessageLength":{"values":["0"]},"AirThreatInfo.ObjectID":{"values":["0"]},"AirThreatInfo.ObjectState":{"values":["0"]},"AirThreatInfo.PositionX":{"values":["0.00000000"]},"AirThreatInfo.PositionY":{"values":["0.00000000"]},"AirThreatInfo.VelocityX":{"values":["0.00000000"]},"AirThreatInfo.VelocityY":{"values":["0.00000000"]}},"length":"40","serialized":"00410000000000000000000000000000000000000000000000000000000000000000000000000000"},{"seq":"61","name":"AirThreatInfo_ToComm","id":"65","owner":"ATSManager","date":"20251103","time":"23:32:27.445","elapsed_time":"21304","instance_id":"0","alignment":"false","omt":"false","type":"interaction","operation":"send","data":{"Header.MessageID":{"values":["65"]},"Header.MessageLength":{"values":["0"]},"AirThreatInfo.ObjectID":{"values":["0"]},"AirThreatInfo.ObjectState":{"values":["0"]},"AirThreatInfo.PositionX":{"values":["0.00000000"]},"AirThreatInfo.PositionY":{"values":["0.00000000"]},"AirThreatInfo.VelocityX":{"values":["0.00000000"]},"AirThreatInfo.VelocityY":{"values":["0.00000000"]}},"length":"40","serialized":"00410000000000000000000000000000000000000000000000000000000000000000000000000000"},{"seq":"62","name":"SimulatorStateToComm","id":"32","owner":"StateManager","date":"20251103","time":"23:32:27.513","elapsed_time":"21372","instance_id":"0","alignment":"false","omt":"false","type":"interaction","operation":"send","data":{"SimulatorID":{"values":["102"]}},"length":"2","serialized":"0066"},{"seq":"63","name":"AirThreatInfo_ToComm","id":"65","owner":"ATSManager","date":"20251103","time":"23:32:27.946","elapsed_time":"21805","instance_id":"0","alignment":"false","omt":"false","type":"interaction","operation":"send","data":{"Header.MessageID":{"values":["65"]},"Header.MessageLength":{"values":["0"]},"AirThreatInfo.ObjectID":{"values":["0"]},"AirThreatInfo.ObjectState":{"values":["0"]},"AirThreatInfo.PositionX":{"values":["0.00000000"]},"AirThreatInfo.PositionY":{"values":["0.00000000"]},"AirThreatInfo.VelocityX":{"values":["0.00000000"]},"AirThreatInfo.VelocityY":{"values":["0.00000000"]}},"length":"40","serialized":"00410000000000000000000000000000000000000000000000000000000000000000000000000000"},{"seq":"64","name":"AirThreatInfo_ToComm","id":"65","owner":"ATSManager","date":"20251103","time":"23:32:28.445","elapsed_time":"22304","instance_id":"0","alignment":"false","omt":"false","type":"interaction","operation":"send","data":{"Header.MessageID":{"values":["65"]},"Header.MessageLength":{"values":["0"]},"AirThreatInfo.ObjectID":{"values":["0"]},"AirThreatInfo.ObjectState":{"values":["0"]},"AirThreatInfo.PositionX":{"values":["0.00000000"]},"AirThreatInfo.PositionY":{"values":["0.00000000"]},"AirThreatInfo.VelocityX":{"values":["0.00000000"]},"AirThreatInfo.VelocityY":{"values":["0.00000000"]}},"length":"40","serialized":"00410000000000000000000000000000000000000000000000000000000000000000000000000000"},{"seq":"65","name":"SimulatorStateToComm","id":"32","owner":"StateManager","date":"20251103","time":"23:32:28.514","elapsed_time":"22373","instance_id":"0","alignment":"false","omt":"false","type":"interaction","operation":"send","data":{"SimulatorID":{"values":["102"]}},"length":"2","serialized":"0066"},{"seq":"66","name":"AirThreatInfo_ToComm","id":"65","owner":"ATSManager","date":"20251103","time":"23:32:28.946","elapsed_time":"22805","instance_id":"0","alignment":"false","omt":"false","type":"interaction","operation":"send","data":{"Header.MessageID":{"values":["65"]},"Header.MessageLength":{"values":["0"]},"AirThreatInfo.ObjectID":{"values":["0"]},"AirThreatInfo.ObjectState":{"values":["0"]},"AirThreatInfo.PositionX":{"values":["0.00000000"]},"AirThreatInfo.PositionY":{"values":["0.00000000"]},"AirThreatInfo.VelocityX":{"values":["0.00000000"]},"AirThreatInfo.VelocityY":{"values":["0.00000000"]}},"length":"40","serialized":"00410000000000000000000000000000000000000000000000000000000000000000000000000000"},{"seq":"67","name":"AirThreatInfo_ToComm","id":"65","owner":"ATSManager","date":"20251103","time":"23:32:29.446","elapsed_time":"23305","instance_id":"0","alignment":"false","omt":"false","type":"interaction","operation":"send","data":{"Header.MessageID":{"values":["65"]},"Header.MessageLength":{"values":["0"]},"AirThreatInfo.ObjectID":{"values":["0"]},"AirThreatInfo.ObjectState":{"values":["0"]},"AirThreatInfo.PositionX":{"values":["0.00000000"]},"AirThreatInfo.PositionY":{"values":["0.00000000"]},"AirThreatInfo.VelocityX":{"values":["0.00000000"]},"AirThreatInfo.VelocityY":{"values":["0.00000000"]}},"length":"40","serialized":"00410000000000000000000000000000000000000000000000000000000000000000000000000000"},{"seq":"68","name":"SimulatorStateToComm","id":"32","owner":"StateManager","date":"20251103","time":"23:32:29.514","elapsed_time":"23373","instance_id":"0","alignment":"false","omt":"false","type":"interaction","operation":"send","data":{"SimulatorID":{"values":["102"]}},"length":"2","serialized":"0066"},{"seq":"69","name":"AirThreatInfo_ToComm","id":"65","owner":"ATSManager","date":"20251103","time":"23:32:29.944","elapsed_time":"23803","instance_id":"0","alignment":"false","omt":"false","type":"interaction","operation":"send","data":{"Header.MessageID":{"values":["65"]},"Header.MessageLength":{"values":["0"]},"AirThreatInfo.ObjectID":{"values":["0"]},"AirThreatInfo.ObjectState":{"values":["0"]},"AirThreatInfo.PositionX":{"values":["0.00000000"]},"AirThreatInfo.PositionY":{"values":["0.00000000"]},"AirThreatInfo.VelocityX":{"values":["0.00000000"]},"AirThreatInfo.VelocityY":{"values":["0.00000000"]}},"length":"40","serialized":"00410000000000000000000000000000000000000000000000000000000000000000000000000000"},{"seq":"70","name":"AirThreatInfo_ToComm","id":"65","owner":"ATSManager","date":"20251103","time":"23:32:30.446","elapsed_time":"24305","instance_id":"0","alignment":"false","omt":"false","type":"interaction","operation":"send","data":{"Header.MessageID":{"values":["65"]},"Header.MessageLength":{"values":["0"]},"AirThreatInfo.ObjectID":{"values":["0"]},"AirThreatInfo.ObjectState":{"values":["0"]},"AirThreatInfo.PositionX":{"values":["0.00000000"]},"AirThreatInfo.PositionY":{"values":["0.00000000"]},"AirThreatInfo.VelocityX":{"values":["0.00000000"]},"AirThreatInfo.VelocityY":{"values":["0.00000000"]}},"length":"40","serialized":"00410000000000000000000000000000000000000000000000000000000000000000000000000000"},{"seq":"71","name":"SimulatorStateToComm","id":"32","owner":"StateManager","date":"20251103","time":"23:32:30.514","elapsed_time":"24373","instance_id":"0","alignment":"false","omt":"false","type":"interaction","operation":"send","data":{"SimulatorID":{"values":["102"]}},"length":"2","serialized":"0066"},{"seq":"72","name":"AirThreatInfo_ToComm","id":"65","owner":"ATSManager","date":"20251103","time":"23:32:30.945","elapsed_time":"24804","instance_id":"0","alignment":"false","omt":"false","type":"interaction","operation":"send","data":{"Header.MessageID":{"values":["65"]},"Header.MessageLength":{"values":["0"]},"AirThreatInfo.ObjectID":{"values":["0"]},"AirThreatInfo.ObjectState":{"values":["0"]},"AirThreatInfo.PositionX":{"values":["0.00000000"]},"AirThreatInfo.PositionY":{"values":["0.00000000"]},"AirThreatInfo.VelocityX":{"values":["0.00000000"]},"AirThreatInfo.VelocityY":{"values":["0.00000000"]}},"length":"40","serialized":"00410000000000000000000000000000000000000000000000000000000000000000000000000000"},{"seq":"73","name":"AirThreatInfo_ToComm","id":"65","owner":"ATSManager","date":"20251103","time":"23:32:31.444","elapsed_time":"25303","instance_id":"0","alignment":"false","omt":"false","type":"interaction","operation":"send","data":{"Header.MessageID":{"values":["65"]},"Header.MessageLength":{"values":["0"]},"AirThreatInfo.ObjectID":{"values":["0"]},"AirThreatInfo.ObjectState":{"values":["0"]},"AirThreatInfo.PositionX":{"values":["0.00000000"]},"AirThreatInfo.PositionY":{"values":["0.00000000"]},"AirThreatInfo.VelocityX":{"values":["0.00000000"]},"AirThreatInfo.VelocityY":{"values":["0.00000000"]}},"length":"40","serialized":"00410000000000000000000000000000000000000000000000000000000000000000000000000000"},{"seq":"74","name":"SimulatorStateToComm","id":"32","owner":"StateManager","date":"20251103","time":"23:32:31.513","elapsed_time":"25372","instance_id":"0","alignment":"false","omt":"false","type":"interaction","operation":"send","data":{"SimulatorID":{"values":["102"]}},"length":"2","serialized":"0066"},{"seq":"75","name":"AirThreatInfo_ToComm","id":"65","owner":"ATSManager","date":"20251103","time":"23:32:31.946","elapsed_time":"25805","instance_id":"0","alignment":"false","omt":"false","type":"interaction","operation":"send","data":{"Header.MessageID":{"values":["65"]},"Header.MessageLength":{"values":["0"]},"AirThreatInfo.ObjectID":{"values":["0"]},"AirThreatInfo.ObjectState":{"values":["0"]},"AirThreatInfo.PositionX":{"values":["0.00000000"]},"AirThreatInfo.PositionY":{"values":["0.00000000"]},"AirThreatInfo.VelocityX":{"values":["0.00000000"]},"AirThreatInfo.VelocityY":{"values":["0.00000000"]}},"length":"40","serialized":"00410000000000000000000000000000000000000000000000000000000000000000000000000000"},{"seq":"76","name":"AirThreatInfo_ToComm","id":"65","owner":"ATSManager","date":"20251103","time":"23:32:32.445","elapsed_time":"26304","instance_id":"0","alignment":"false","omt":"false","type":"interaction","operation":"send","data":{"Header.MessageID":{"values":["65"]},"Header.MessageLength":{"values":["0"]},"AirThreatInfo.ObjectID":{"values":["0"]},"AirThreatInfo.ObjectState":{"values":["0"]},"AirThreatInfo.PositionX":{"values":["0.00000000"]},"AirThreatInfo.PositionY":{"values":["0.00000000"]},"AirThreatInfo.VelocityX":{"values":["0.00000000"]},"AirThreatInfo.VelocityY":{"values":["0.00000000"]}},"length":"40","serialized":"00410000000000000000000000000000000000000000000000000000000000000000000000000000"},{"seq":"77","name":"SimulatorStateToComm","id":"32","owner":"StateManager","date":"20251103","time":"23:32:32.513","elapsed_time":"26372","instance_id":"0","alignment":"false","omt":"false","type":"interaction","operation":"send","data":{"SimulatorID":{"values":["102"]}},"length":"2","serialized":"0066"},{"seq":"78","name":"AirThreatInfo_ToComm","id":"65","owner":"ATSManager","date":"20251103","time":"23:32:32.945","elapsed_time":"26804","instance_id":"0","alignment":"false","omt":"false","type":"interaction","operation":"send","data":{"Header.MessageID":{"values":["65"]},"Header.MessageLength":{"values":["0"]},"AirThreatInfo.ObjectID":{"values":["0"]},"AirThreatInfo.ObjectState":{"values":["0"]},"AirThreatInfo.PositionX":{"values":["0.00000000"]},"AirThreatInfo.PositionY":{"values":["0.00000000"]},"AirThreatInfo.VelocityX":{"values":["0.00000000"]},"AirThreatInfo.VelocityY":{"values":["0.00000000"]}},"length":"40","serialized":"00410000000000000000000000000000000000000000000000000000000000000000000000000000"},{"seq":"79","name":"AirThreatInfo_ToComm","id":"65","owner":"ATSManager","date":"20251103","time":"23:32:33.446","elapsed_time":"27305","instance_id":"0","alignment":"false","omt":"false","type":"interaction","operation":"send","data":{"Header.MessageID":{"values":["65"]},"Header.MessageLength":{"values":["0"]},"AirThreatInfo.ObjectID":{"values":["0"]},"AirThreatInfo.ObjectState":{"values":["0"]},"AirThreatInfo.PositionX":{"values":["0.00000000"]},"AirThreatInfo.PositionY":{"values":["0.00000000"]},"AirThreatInfo.VelocityX":{"values":["0.00000000"]},"AirThreatInfo.VelocityY":{"values":["0.00000000"]}},"length":"40","serialized":"00410000000000000000000000000000000000000000000000000000000000000000000000000000"},{"seq":"80","name":"SimulatorStateToComm","id":"32","owner":"StateManager","date":"20251103","time":"23:32:33.514","elapsed_time":"27373","instance_id":"0","alignment":"false","omt":"false","type":"interaction","operation":"send","data":{"SimulatorID":{"values":["102"]}},"length":"2","serialized":"0066"},{"seq":"81","name":"AirThreatInfo_ToComm","id":"65","owner":"ATSManager","date":"20251103","time":"23:32:33.945","elapsed_time":"27804","instance_id":"0","alignment":"false","omt":"false","type":"interaction","operation":"send","data":{"Header.MessageID":{"values":["65"]},"Header.MessageLength":{"values":["0"]},"AirThreatInfo.ObjectID":{"values":["0"]},"AirThreatInfo.ObjectState":{"values":["0"]},"AirThreatInfo.PositionX":{"values":["0.00000000"]},"AirThreatInfo.PositionY":{"values":["0.00000000"]},"AirThreatInfo.VelocityX":{"values":["0.00000000"]},"AirThreatInfo.VelocityY":{"values":["0.00000000"]}},"length":"40","serialized":"00410000000000000000000000000000000000000000000000000000000000000000000000000000"},{"seq":"82","name":"AirThreatInfo_ToComm","id":"65","owner":"ATSManager","date":"20251103","time":"23:32:34.445","elapsed_time":"28304","instance_id":"0","alignment":"false","omt":"false","type":"interaction","operation":"send","data":{"Header.MessageID":{"values":["65"]},"Header.MessageLength":{"values":["0"]},"AirThreatInfo.ObjectID":{"values":["0"]},"AirThreatInfo.ObjectState":{"values":["0"]},"AirThreatInfo.PositionX":{"values":["0.00000000"]},"AirThreatInfo.PositionY":{"values":["0.00000000"]},"AirThreatInfo.VelocityX":{"values":["0.00000000"]},"AirThreatInfo.VelocityY":{"values":["0.00000000"]}},"length":"40","serialized":"00410000000000000000000000000000000000000000000000000000000000000000000000000000"},{"seq":"83","name":"SimulatorStateToComm","id":"32","owner":"StateManager","date":"20251103","time":"23:32:34.513","elapsed_time":"28372","instance_id":"0","alignment":"false","omt":"false","type":"interaction","operation":"send","data":{"SimulatorID":{"values":["102"]}},"length":"2","serialized":"0066"},{"seq":"84","name":"AirThreatInfo_ToComm","id":"65","owner":"ATSManager","date":"20251103","time":"23:32:34.946","elapsed_time":"28805","instance_id":"0","alignment":"false","omt":"false","type":"interaction","operation":"send","data":{"Header.MessageID":{"values":["65"]},"Header.MessageLength":{"values":["0"]},"AirThreatInfo.ObjectID":{"values":["0"]},"AirThreatInfo.ObjectState":{"values":["0"]},"AirThreatInfo.PositionX":{"values":["0.00000000"]},"AirThreatInfo.PositionY":{"values":["0.00000000"]},"AirThreatInfo.VelocityX":{"values":["0.00000000"]},"AirThreatInfo.VelocityY":{"values":["0.00000000"]}},"length":"40","serialized":"00410000000000000000000000000000000000000000000000000000000000000000000000000000"},{"seq":"85","name":"AirThreatInfo_ToComm","id":"65","owner":"ATSManager","date":"20251103","time":"23:32:35.445","elapsed_time":"29304","instance_id":"0","alignment":"false","omt":"false","type":"interaction","operation":"send","data":{"Header.MessageID":{"values":["65"]},"Header.MessageLength":{"values":["0"]},"AirThreatInfo.ObjectID":{"values":["0"]},"AirThreatInfo.ObjectState":{"values":["0"]},"AirThreatInfo.PositionX":{"values":["0.00000000"]},"AirThreatInfo.PositionY":{"values":["0.00000000"]},"AirThreatInfo.VelocityX":{"values":["0.00000000"]},"AirThreatInfo.VelocityY":{"values":["0.00000000"]}},"length":"40","serialized":"00410000000000000000000000000000000000000000000000000000000000000000000000000000"},{"seq":"86","name":"SimulatorStateToComm","id":"32","owner":"StateManager","date":"20251103","time":"23:32:35.514","elapsed_time":"29373","instance_id":"0","alignment":"false","omt":"false","type":"interaction","operation":"send","data":{"SimulatorID":{"values":["102"]}},"length":"2","serialized":"0066"},{"seq":"87","name":"AirThreatInfo_ToComm","id":"65","owner":"ATSManager","date":"20251103","time":"23:32:35.945","elapsed_time":"29804","instance_id":"0","alignment":"false","omt":"false","type":"interaction","operation":"send","data":{"Header.MessageID":{"values":["65"]},"Header.MessageLength":{"values":["0"]},"AirThreatInfo.ObjectID":{"values":["0"]},"AirThreatInfo.ObjectState":{"values":["0"]},"AirThreatInfo.PositionX":{"values":["0.00000000"]},"AirThreatInfo.PositionY":{"values":["0.00000000"]},"AirThreatInfo.VelocityX":{"values":["0.00000000"]},"AirThreatInfo.VelocityY":{"values":["0.00000000"]}},"length":"40","serialized":"00410000000000000000000000000000000000000000000000000000000000000000000000000000"},{"seq":"88","name":"AirThreatInfo_ToComm","id":"65","owner":"ATSManager","date":"20251103","time":"23:32:36.446","elapsed_time":"30305","instance_id":"0","alignment":"false","omt":"false","type":"interaction","operation":"send","data":{"Header.MessageID":{"values":["65"]},"Header.MessageLength":{"values":["0"]},"AirThreatInfo.ObjectID":{"values":["0"]},"AirThreatInfo.ObjectState":{"values":["0"]},"AirThreatInfo.PositionX":{"values":["0.00000000"]},"AirThreatInfo.PositionY":{"values":["0.00000000"]},"AirThreatInfo.VelocityX":{"values":["0.00000000"]},"AirThreatInfo.VelocityY":{"values":["0.00000000"]}},"length":"40","serialized":"00410000000000000000000000000000000000000000000000000000000000000000000000000000"},{"seq":"89","name":"SimulatorStateToComm","id":"32","owner":"StateManager","date":"20251103","time":"23:32:36.514","elapsed_time":"30373","instance_id":"0","alignment":"false","omt":"false","type":"interaction","operation":"send","data":{"SimulatorID":{"values":["102"]}},"length":"2","serialized":"0066"},{"seq":"90","name":"AirThreatInfo_ToComm","id":"65","owner":"ATSManager","date":"20251103","time":"23:32:36.946","elapsed_time":"30805","instance_id":"0","alignment":"false","omt":"false","type":"interaction","operation":"send","data":{"Header.MessageID":{"values":["65"]},"Header.MessageLength":{"values":["0"]},"AirThreatInfo.ObjectID":{"values":["0"]},"AirThreatInfo.ObjectState":{"values":["0"]},"AirThreatInfo.PositionX":{"values":["0.00000000"]},"AirThreatInfo.PositionY":{"values":["0.00000000"]},"AirThreatInfo.VelocityX":{"values":["0.00000000"]},"AirThreatInfo.VelocityY":{"values":["0.00000000"]}},"length":"40","serialized":"00410000000000000000000000000000000000000000000000000000000000000000000000000000"},{"seq":"91","name":"AirThreatInfo_ToComm","id":"65","owner":"ATSManager","date":"20251103","time":"23:32:37.445","elapsed_time":"31304","instance_id":"0","alignment":"false","omt":"false","type":"interaction","operation":"send","data":{"Header.MessageID":{"values":["65"]},"Header.MessageLength":{"values":["0"]},"AirThreatInfo.ObjectID":{"values":["0"]},"AirThreatInfo.ObjectState":{"values":["0"]},"AirThreatInfo.PositionX":{"values":["0.00000000"]},"AirThreatInfo.PositionY":{"values":["0.00000000"]},"AirThreatInfo.VelocityX":{"values":["0.00000000"]},"AirThreatInfo.VelocityY":{"values":["0.00000000"]}},"length":"40","serialized":"00410000000000000000000000000000000000000000000000000000000000000000000000000000"},{"seq":"92","name":"SimulatorStateToComm","id":"32","owner":"StateManager","date":"20251103","time":"23:32:37.513","elapsed_time":"31372","instance_id":"0","alignment":"false","omt":"false","type":"interaction","operation":"send","data":{"SimulatorID":{"values":["102"]}},"length":"2","serialized":"0066"},{"seq":"93","name":"AirThreatInfo_ToComm","id":"65","owner":"ATSManager","date":"20251103","time":"23:32:37.944","elapsed_time":"31803","instance_id":"0","alignment":"false","omt":"false","type":"interaction","operation":"send","data":{"Header.MessageID":{"values":["65"]},"Header.MessageLength":{"values":["0"]},"AirThreatInfo.ObjectID":{"values":["0"]},"AirThreatInfo.ObjectState":{"values":["0"]},"AirThreatInfo.PositionX":{"values":["0.00000000"]},"AirThreatInfo.PositionY":{"values":["0.00000000"]},"AirThreatInfo.VelocityX":{"values":["0.00000000"]},"AirThreatInfo.VelocityY":{"values":["0.00000000"]}},"length":"40","serialized":"00410000000000000000000000000000000000000000000000000000000000000000000000000000"},{"seq":"94","name":"AirThreatInfo_ToComm","id":"65","owner":"ATSManager","date":"20251103","time":"23:32:38.446","elapsed_time":"32305","instance_id":"0","alignment":"false","omt":"false","type":"interaction","operation":"send","data":{"Header.MessageID":{"values":["65"]},"Header.MessageLength":{"values":["0"]},"AirThreatInfo.ObjectID":{"values":["0"]},"AirThreatInfo.ObjectState":{"values":["0"]},"AirThreatInfo.PositionX":{"values":["0.00000000"]},"AirThreatInfo.PositionY":{"values":["0.00000000"]},"AirThreatInfo.VelocityX":{"values":["0.00000000"]},"AirThreatInfo.VelocityY":{"values":["0.00000000"]}},"length":"40","serialized":"00410000000000000000000000000000000000000000000000000000000000000000000000000000"},{"seq":"95","name":"SimulatorStateToComm","id":"32","owner":"StateManager","date":"20251103","time":"23:32:38.514","elapsed_time":"32373","instance_id":"0","alignment":"false","omt":"false","type":"interaction","operation":"send","data":{"SimulatorID":{"values":["102"]}},"length":"2","serialized":"0066"},{"seq":"96","name":"AirThreatInfo_ToComm","id":"65","owner":"ATSManager","date":"20251103","time":"23:32:38.945","elapsed_time":"32804","instance_id":"0","alignment":"false","omt":"false","type":"interaction","operation":"send","data":{"Header.MessageID":{"values":["65"]},"Header.MessageLength":{"values":["0"]},"AirThreatInfo.ObjectID":{"values":["0"]},"AirThreatInfo.ObjectState":{"values":["0"]},"AirThreatInfo.PositionX":{"values":["0.00000000"]},"AirThreatInfo.PositionY":{"values":["0.00000000"]},"AirThreatInfo.VelocityX":{"values":["0.00000000"]},"AirThreatInfo.VelocityY":{"values":["0.00000000"]}},"length":"40","serialized":"00410000000000000000000000000000000000000000000000000000000000000000000000000000"},{"seq":"97","name":"AirThreatInfo_ToComm","id":"65","owner":"ATSManager","date":"20251103","time":"23:32:39.444","elapsed_time":"33303","instance_id":"0","alignment":"false","omt":"false","type":"interaction","operation":"send","data":{"Header.MessageID":{"values":["65"]},"Header.MessageLength":{"values":["0"]},"AirThreatInfo.ObjectID":{"values":["0"]},"AirThreatInfo.ObjectState":{"values":["0"]},"AirThreatInfo.PositionX":{"values":["0.00000000"]},"AirThreatInfo.PositionY":{"values":["0.00000000"]},"AirThreatInfo.VelocityX":{"values":["0.00000000"]},"AirThreatInfo.VelocityY":{"values":["0.00000000"]}},"length":"40","serialized":"00410000000000000000000000000000000000000000000000000000000000000000000000000000"},{"seq":"98","name":"SimulatorStateToComm","id":"32","owner":"StateManager","date":"20251103","time":"23:32:39.514","elapsed_time":"33373","instance_id":"0","alignment":"false","omt":"false","type":"interaction","operation":"send","data":{"SimulatorID":{"values":["102"]}},"length":"2","serialized":"0066"},{"seq":"99","name":"AirThreatInfo_ToComm","id":"65","owner":"ATSManager","date":"20251103","time":"23:32:39.946","elapsed_time":"33805","instance_id":"0","alignment":"false","omt":"false","type":"interaction","operation":"send","data":{"Header.MessageID":{"values":["65"]},"Header.MessageLength":{"values":["0"]},"AirThreatInfo.ObjectID":{"values":["0"]},"AirThreatInfo.ObjectState":{"values":["0"]},"AirThreatInfo.PositionX":{"values":["0.00000000"]},"AirThreatInfo.PositionY":{"values":["0.00000000"]},"AirThreatInfo.VelocityX":{"values":["0.00000000"]},"AirThreatInfo.VelocityY":{"values":["0.00000000"]}},"length":"40","serialized":"00410000000000000000000000000000000000000000000000000000000000000000000000000000"},{"seq":"100","name":"AirThreatInfo_ToComm","id":"65","owner":"ATSManager","date":"20251103","time":"23:32:40.445","elapsed_time":"34304","instance_id":"0","alignment":"false","omt":"false","type":"interaction","operation":"send","data":{"Header.MessageID":{"values":["65"]},"Header.MessageLength":{"values":["0"]},"AirThreatInfo.ObjectID":{"values":["0"]},"AirThreatInfo.ObjectState":{"values":["0"]},"AirThreatInfo.PositionX":{"values":["0.00000000"]},"AirThreatInfo.PositionY":{"values":["0.00000000"]},"AirThreatInfo.VelocityX":{"values":["0.00000000"]},"AirThreatInfo.VelocityY":{"values":["0.00000000"]}},"length":"40","serialized":"00410000000000000000000000000000000000000000000000000000000000000000000000000000"},{"seq":"101","name":"SimulatorStateToComm","id":"32","owner":"StateManager","date":"20251103","time":"23:32:40.513","elapsed_time":"34372","instance_id":"0","alignment":"false","omt":"false","type":"interaction","operation":"send","data":{"SimulatorID":{"values":["102"]}},"length":"2","serialized":"0066"},{"seq":"102","name":"AirThreatInfo_ToComm","id":"65","owner":"ATSManager","date":"20251103","time":"23:32:40.945","elapsed_time":"34804","instance_id":"0","alignment":"false","omt":"false","type":"interaction","operation":"send","data":{"Header.MessageID":{"values":["65"]},"Header.MessageLength":{"values":["0"]},"AirThreatInfo.ObjectID":{"values":["0"]},"AirThreatInfo.ObjectState":{"values":["0"]},"AirThreatInfo.PositionX":{"values":["0.00000000"]},"AirThreatInfo.PositionY":{"values":["0.00000000"]},"AirThreatInfo.VelocityX":{"values":["0.00000000"]},"AirThreatInfo.VelocityY":{"values":["0.00000000"]}},"length":"40","serialized":"00410000000000000000000000000000000000000000000000000000000000000000000000000000"},{"seq":"103","name":"AirThreatInfo_ToComm","id":"65","owner":"ATSManager","date":"20251103","time":"23:32:41.446","elapsed_time":"35305","instance_id":"0","alignment":"false","omt":"false","type":"interaction","operation":"send","data":{"Header.MessageID":{"values":["65"]},"Header.MessageLength":{"values":["0"]},"AirThreatInfo.ObjectID":{"values":["0"]},"AirThreatInfo.ObjectState":{"values":["0"]},"AirThreatInfo.PositionX":{"values":["0.00000000"]},"AirThreatInfo.PositionY":{"values":["0.00000000"]},"AirThreatInfo.VelocityX":{"values":["0.00000000"]},"AirThreatInfo.VelocityY":{"values":["0.00000000"]}},"length":"40","serialized":"00410000000000000000000000000000000000000000000000000000000000000000000000000000"},{"seq":"104","name":"SimulatorStateToComm","id":"32","owner":"StateManager","date":"20251103","time":"23:32:41.514","elapsed_time":"35373","instance_id":"0","alignment":"false","omt":"false","type":"interaction","operation":"send","data":{"SimulatorID":{"values":["102"]}},"length":"2","serialized":"0066"},{"seq":"105","name":"AirThreatInfo_ToComm","id":"65","owner":"ATSManager","date":"20251103","time":"23:32:41.945","elapsed_time":"35804","instance_id":"0","alignment":"false","omt":"false","type":"interaction","operation":"send","data":{"Header.MessageID":{"values":["65"]},"Header.MessageLength":{"values":["0"]},"AirThreatInfo.ObjectID":{"values":["0"]},"AirThreatInfo.ObjectState":{"values":["0"]},"AirThreatInfo.PositionX":{"values":["0.00000000"]},"AirThreatInfo.PositionY":{"values":["0.00000000"]},"AirThreatInfo.VelocityX":{"values":["0.00000000"]},"AirThreatInfo.VelocityY":{"values":["0.00000000"]}},"length":"40","serialized":"00410000000000000000000000000000000000000000000000000000000000000000000000000000"},{"seq":"106","name":"AirThreatInfo_ToComm","id":"65","owner":"ATSManager","date":"20251103","time":"23:32:42.445","elapsed_time":"36304","instance_id":"0","alignment":"false","omt":"false","type":"interaction","operation":"send","data":{"Header.MessageID":{"values":["65"]},"Header.MessageLength":{"values":["0"]},"AirThreatInfo.ObjectID":{"values":["0"]},"AirThreatInfo.ObjectState":{"values":["0"]},"AirThreatInfo.PositionX":{"values":["0.00000000"]},"AirThreatInfo.PositionY":{"values":["0.00000000"]},"AirThreatInfo.VelocityX":{"values":["0.00000000"]},"AirThreatInfo.VelocityY":{"values":["0.00000000"]}},"length":"40","serialized":"00410000000000000000000000000000000000000000000000000000000000000000000000000000"},{"seq":"107","name":"SimulatorStateToComm","id":"32","owner":"StateManager","date":"20251103","time":"23:32:42.514","elapsed_time":"36373","instance_id":"0","alignment":"false","omt":"false","type":"interaction","operation":"send","data":{"SimulatorID":{"values":["102"]}},"length":"2","serialized":"0066"},{"seq":"108","name":"AirThreatInfo_ToComm","id":"65","owner":"ATSManager","date":"20251103","time":"23:32:42.946","elapsed_time":"36805","instance_id":"0","alignment":"false","omt":"false","type":"interaction","operation":"send","data":{"Header.MessageID":{"values":["65"]},"Header.MessageLength":{"values":["0"]},"AirThreatInfo.ObjectID":{"values":["0"]},"AirThreatInfo.ObjectState":{"values":["0"]},"AirThreatInfo.PositionX":{"values":["0.00000000"]},"AirThreatInfo.PositionY":{"values":["0.00000000"]},"AirThreatInfo.VelocityX":{"values":["0.00000000"]},"AirThreatInfo.VelocityY":{"values":["0.00000000"]}},"length":"40","serialized":"00410000000000000000000000000000000000000000000000000000000000000000000000000000"},{"seq":"109","name":"AirThreatInfo_ToComm","id":"65","owner":"ATSManager","date":"20251103","time":"23:32:43.445","elapsed_time":"37304","instance_id":"0","alignment":"false","omt":"false","type":"interaction","operation":"send","data":{"Header.MessageID":{"values":["65"]},"Header.MessageLength":{"values":["0"]},"AirThreatInfo.ObjectID":{"values":["0"]},"AirThreatInfo.ObjectState":{"values":["0"]},"AirThreatInfo.PositionX":{"values":["0.00000000"]},"AirThreatInfo.PositionY":{"values":["0.00000000"]},"AirThreatInfo.VelocityX":{"values":["0.00000000"]},"AirThreatInfo.VelocityY":{"values":["0.00000000"]}},"length":"40","serialized":"00410000000000000000000000000000000000000000000000000000000000000000000000000000"},{"seq":"110","name":"SimulatorStateToComm","id":"32","owner":"StateManager","date":"20251103","time":"23:32:43.514","elapsed_time":"37373","instance_id":"0","alignment":"false","omt":"false","type":"interaction","operation":"send","data":{"SimulatorID":{"values":["102"]}},"length":"2","serialized":"0066"},{"seq":"111","name":"AirThreatInfo_ToComm","id":"65","owner":"ATSManager","date":"20251103","time":"23:32:43.945","elapsed_time":"37804","instance_id":"0","alignment":"false","omt":"false","type":"interaction","operation":"send","data":{"Header.MessageID":{"values":["65"]},"Header.MessageLength":{"values":["0"]},"AirThreatInfo.ObjectID":{"values":["0"]},"AirThreatInfo.ObjectState":{"values":["0"]},"AirThreatInfo.PositionX":{"values":["0.00000000"]},"AirThreatInfo.PositionY":{"values":["0.00000000"]},"AirThreatInfo.VelocityX":{"values":["0.00000000"]},"AirThreatInfo.VelocityY":{"values":["0.00000000"]}},"length":"40","serialized":"00410000000000000000000000000000000000000000000000000000000000000000000000000000"},{"seq":"112","name":"AirThreatInfo_ToComm","id":"65","owner":"ATSManager","date":"20251103","time":"23:32:44.445","elapsed_time":"38304","instance_id":"0","alignment":"false","omt":"false","type":"interaction","operation":"send","data":{"Header.MessageID":{"values":["65"]},"Header.MessageLength":{"values":["0"]},"AirThreatInfo.ObjectID":{"values":["0"]},"AirThreatInfo.ObjectState":{"values":["0"]},"AirThreatInfo.PositionX":{"values":["0.00000000"]},"AirThreatInfo.PositionY":{"values":["0.00000000"]},"AirThreatInfo.VelocityX":{"values":["0.00000000"]},"AirThreatInfo.VelocityY":{"values":["0.00000000"]}},"length":"40","serialized":"00410000000000000000000000000000000000000000000000000000000000000000000000000000"},{"seq":"113","name":"SimulatorStateToComm","id":"32","owner":"StateManager","date":"20251103","time":"23:32:44.514","elapsed_time":"38373","instance_id":"0","alignment":"false","omt":"false","type":"interaction","operation":"send","data":{"SimulatorID":{"values":["102"]}},"length":"2","serialized":"0066"},{"seq":"114","name":"AirThreatInfo_ToComm","id":"65","owner":"ATSManager","date":"20251103","time":"23:32:44.946","elapsed_time":"38805","instance_id":"0","alignment":"false","omt":"false","type":"interaction","operation":"send","data":{"Header.MessageID":{"values":["65"]},"Header.MessageLength":{"values":["0"]},"AirThreatInfo.ObjectID":{"values":["0"]},"AirThreatInfo.ObjectState":{"values":["0"]},"AirThreatInfo.PositionX":{"values":["0.00000000"]},"AirThreatInfo.PositionY":{"values":["0.00000000"]},"AirThreatInfo.VelocityX":{"values":["0.00000000"]},"AirThreatInfo.VelocityY":{"values":["0.00000000"]}},"length":"40","serialized":"00410000000000000000000000000000000000000000000000000000000000000000000000000000"},{"seq":"115","name":"AirThreatInfo_ToComm","id":"65","owner":"ATSManager","date":"20251103","time":"23:32:45.446","elapsed_time":"39305","instance_id":"0","alignment":"false","omt":"false","type":"interaction","operation":"send","data":{"Header.MessageID":{"values":["65"]},"Header.MessageLength":{"values":["0"]},"AirThreatInfo.ObjectID":{"values":["0"]},"AirThreatInfo.ObjectState":{"values":["0"]},"AirThreatInfo.PositionX":{"values":["0.00000000"]},"AirThreatInfo.PositionY":{"values":["0.00000000"]},"AirThreatInfo.VelocityX":{"values":["0.00000000"]},"AirThreatInfo.VelocityY":{"values":["0.00000000"]}},"length":"40","serialized":"00410000000000000000000000000000000000000000000000000000000000000000000000000000"},{"seq":"116","name":"SimulatorStateToComm","id":"32","owner":"StateManager","date":"20251103","time":"23:32:45.514","elapsed_time":"39373","instance_id":"0","alignment":"false","omt":"false","type":"interaction","operation":"send","data":{"SimulatorID":{"values":["102"]}},"length":"2","serialized":"0066"},{"seq":"117","name":"AirThreatInfo_ToComm","id":"65","owner":"ATSManager","date":"20251103","time":"23:32:45.944","elapsed_time":"39803","instance_id":"0","alignment":"false","omt":"false","type":"interaction","operation":"send","data":{"Header.MessageID":{"values":["65"]},"Header.MessageLength":{"values":["0"]},"AirThreatInfo.ObjectID":{"values":["0"]},"AirThreatInfo.ObjectState":{"values":["0"]},"AirThreatInfo.PositionX":{"values":["0.00000000"]},"AirThreatInfo.PositionY":{"values":["0.00000000"]},"AirThreatInfo.VelocityX":{"values":["0.00000000"]},"AirThreatInfo.VelocityY":{"values":["0.00000000"]}},"length":"40","serialized":"00410000000000000000000000000000000000000000000000000000000000000000000000000000"},{"seq":"118","name":"AirThreatInfo_ToComm","id":"65","owner":"ATSManager","date":"20251103","time":"23:32:46.446","elapsed_time":"40305","instance_id":"0","alignment":"false","omt":"false","type":"interaction","operation":"send","data":{"Header.MessageID":{"values":["65"]},"Header.MessageLength":{"values":["0"]},"AirThreatInfo.ObjectID":{"values":["0"]},"AirThreatInfo.ObjectState":{"values":["0"]},"AirThreatInfo.PositionX":{"values":["0.00000000"]},"AirThreatInfo.PositionY":{"values":["0.00000000"]},"AirThreatInfo.VelocityX":{"values":["0.00000000"]},"AirThreatInfo.VelocityY":{"values":["0.00000000"]}},"length":"40","serialized":"00410000000000000000000000000000000000000000000000000000000000000000000000000000"},{"seq":"119","name":"SimulatorStateToComm","id":"32","owner":"StateManager","date":"20251103","time":"23:32:46.514","elapsed_time":"40373","instance_id":"0","alignment":"false","omt":"false","type":"interaction","operation":"send","data":{"SimulatorID":{"values":["102"]}},"length":"2","serialized":"0066"},{"seq":"120","name":"AirThreatInfo_ToComm","id":"65","owner":"ATSManager","date":"20251103","time":"23:32:46.946","elapsed_time":"40805","instance_id":"0","alignment":"false","omt":"false","type":"interaction","operation":"send","data":{"Header.MessageID":{"values":["65"]},"Header.MessageLength":{"values":["0"]},"AirThreatInfo.ObjectID":{"values":["0"]},"AirThreatInfo.ObjectState":{"values":["0"]},"AirThreatInfo.PositionX":{"values":["0.00000000"]},"AirThreatInfo.PositionY":{"values":["0.00000000"]},"AirThreatInfo.VelocityX":{"values":["0.00000000"]},"AirThreatInfo.VelocityY":{"values":["0.00000000"]}},"length":"40","serialized":"00410000000000000000000000000000000000000000000000000000000000000000000000000000"},{"seq":"121","name":"AirThreatInfo_ToComm","id":"65","owner":"ATSManager","date":"20251103","time":"23:32:47.444","elapsed_time":"41303","instance_id":"0","alignment":"false","omt":"false","type":"interaction","operation":"send","data":{"Header.MessageID":{"values":["65"]},"Header.MessageLength":{"values":["0"]},"AirThreatInfo.ObjectID":{"values":["0"]},"AirThreatInfo.ObjectState":{"values":["0"]},"AirThreatInfo.PositionX":{"values":["0.00000000"]},"AirThreatInfo.PositionY":{"values":["0.00000000"]},"AirThreatInfo.VelocityX":{"values":["0.00000000"]},"AirThreatInfo.VelocityY":{"values":["0.00000000"]}},"length":"40","serialized":"00410000000000000000000000000000000000000000000000000000000000000000000000000000"},{"seq":"122","name":"SimulatorStateToComm","id":"32","owner":"StateManager","date":"20251103","time":"23:32:47.513","elapsed_time":"41372","instance_id":"0","alignment":"false","omt":"false","type":"interaction","operation":"send","data":{"SimulatorID":{"values":["102"]}},"length":"2","serialized":"0066"},{"seq":"123","name":"AirThreatInfo_ToComm","id":"65","owner":"ATSManager","date":"20251103","time":"23:32:47.946","elapsed_time":"41805","instance_id":"0","alignment":"false","omt":"false","type":"interaction","operation":"send","data":{"Header.MessageID":{"values":["65"]},"Header.MessageLength":{"values":["0"]},"AirThreatInfo.ObjectID":{"values":["0"]},"AirThreatInfo.ObjectState":{"values":["0"]},"AirThreatInfo.PositionX":{"values":["0.00000000"]},"AirThreatInfo.PositionY":{"values":["0.00000000"]},"AirThreatInfo.VelocityX":{"values":["0.00000000"]},"AirThreatInfo.VelocityY":{"values":["0.00000000"]}},"length":"40","serialized":"00410000000000000000000000000000000000000000000000000000000000000000000000000000"},{"seq":"124","name":"AirThreatInfo_ToComm","id":"65","owner":"ATSManager","date":"20251103","time":"23:32:48.445","elapsed_time":"42304","instance_id":"0","alignment":"false","omt":"false","type":"interaction","operation":"send","data":{"Header.MessageID":{"values":["65"]},"Header.MessageLength":{"values":["0"]},"AirThreatInfo.ObjectID":{"values":["0"]},"AirThreatInfo.ObjectState":{"values":["0"]},"AirThreatInfo.PositionX":{"values":["0.00000000"]},"AirThreatInfo.PositionY":{"values":["0.00000000"]},"AirThreatInfo.VelocityX":{"values":["0.00000000"]},"AirThreatInfo.VelocityY":{"values":["0.00000000"]}},"length":"40","serialized":"00410000000000000000000000000000000000000000000000000000000000000000000000000000"},{"seq":"125","name":"SimulatorStateToComm","id":"32","owner":"StateManager","date":"20251103","time":"23:32:48.514","elapsed_time":"42373","instance_id":"0","alignment":"false","omt":"false","type":"interaction","operation":"send","data":{"SimulatorID":{"values":["102"]}},"length":"2","serialized":"0066"},{"seq":"126","name":"AirThreatInfo_ToComm","id":"65","owner":"ATSManager","date":"20251103","time":"23:32:48.945","elapsed_time":"42804","instance_id":"0","alignment":"false","omt":"false","type":"interaction","operation":"send","data":{"Header.MessageID":{"values":["65"]},"Header.MessageLength":{"values":["0"]},"AirThreatInfo.ObjectID":{"values":["0"]},"AirThreatInfo.ObjectState":{"values":["0"]},"AirThreatInfo.PositionX":{"values":["0.00000000"]},"AirThreatInfo.PositionY":{"values":["0.00000000"]},"AirThreatInfo.VelocityX":{"values":["0.00000000"]},"AirThreatInfo.VelocityY":{"values":["0.00000000"]}},"length":"40","serialized":"00410000000000000000000000000000000000000000000000000000000000000000000000000000"},{"seq":"127","name":"AirThreatInfo_ToComm","id":"65","owner":"ATSManager","date":"20251103","time":"23:32:49.445","elapsed_time":"43304","instance_id":"0","alignment":"false","omt":"false","type":"interaction","operation":"send","data":{"Header.MessageID":{"values":["65"]},"Header.MessageLength":{"values":["0"]},"AirThreatInfo.ObjectID":{"values":["0"]},"AirThreatInfo.ObjectState":{"values":["0"]},"AirThreatInfo.PositionX":{"values":["0.00000000"]},"AirThreatInfo.PositionY":{"values":["0.00000000"]},"AirThreatInfo.VelocityX":{"values":["0.00000000"]},"AirThreatInfo.VelocityY":{"values":["0.00000000"]}},"length":"40","serialized":"00410000000000000000000000000000000000000000000000000000000000000000000000000000"},{"seq":"128","name":"SimulatorStateToComm","id":"32","owner":"StateManager","date":"20251103","time":"23:32:49.514","elapsed_time":"43373","instance_id":"0","alignment":"false","omt":"false","type":"interaction","operation":"send","data":{"SimulatorID":{"values":["102"]}},"length":"2","serialized":"0066"},{"seq":"129","name":"AirThreatInfo_ToComm","id":"65","owner":"ATSManager","date":"20251103","time":"23:32:49.944","elapsed_time":"43803","instance_id":"0","alignment":"false","omt":"false","type":"interaction","operation":"send","data":{"Header.MessageID":{"values":["65"]},"Header.MessageLength":{"values":["0"]},"AirThreatInfo.ObjectID":{"values":["0"]},"AirThreatInfo.ObjectState":{"values":["0"]},"AirThreatInfo.PositionX":{"values":["0.00000000"]},"AirThreatInfo.PositionY":{"values":["0.00000000"]},"AirThreatInfo.VelocityX":{"values":["0.00000000"]},"AirThreatInfo.VelocityY":{"values":["0.00000000"]}},"length":"40","serialized":"00410000000000000000000000000000000000000000000000000000000000000000000000000000"},{"seq":"130","name":"AirThreatInfo_ToComm","id":"65","owner":"ATSManager","date":"20251103","time":"23:32:50.446","elapsed_time":"44305","instance_id":"0","alignment":"false","omt":"false","type":"interaction","operation":"send","data":{"Header.MessageID":{"values":["65"]},"Header.MessageLength":{"values":["0"]},"AirThreatInfo.ObjectID":{"values":["0"]},"AirThreatInfo.ObjectState":{"values":["0"]},"AirThreatInfo.PositionX":{"values":["0.00000000"]},"AirThreatInfo.PositionY":{"values":["0.00000000"]},"AirThreatInfo.VelocityX":{"values":["0.00000000"]},"AirThreatInfo.VelocityY":{"values":["0.00000000"]}},"length":"40","serialized":"00410000000000000000000000000000000000000000000000000000000000000000000000000000"},{"seq":"131","name":"SimulatorStateToComm","id":"32","owner":"StateManager","date":"20251103","time":"23:32:50.514","elapsed_time":"44373","instance_id":"0","alignment":"false","omt":"false","type":"interaction","operation":"send","data":{"SimulatorID":{"values":["102"]}},"length":"2","serialized":"0066"},{"seq":"132","name":"AirThreatInfo_ToComm","id":"65","owner":"ATSManager","date":"20251103","time":"23:32:50.945","elapsed_time":"44804","instance_id":"0","alignment":"false","omt":"false","type":"interaction","operation":"send","data":{"Header.MessageID":{"values":["65"]},"Header.MessageLength":{"values":["0"]},"AirThreatInfo.ObjectID":{"values":["0"]},"AirThreatInfo.ObjectState":{"values":["0"]},"AirThreatInfo.PositionX":{"values":["0.00000000"]},"AirThreatInfo.PositionY":{"values":["0.00000000"]},"AirThreatInfo.VelocityX":{"values":["0.00000000"]},"AirThreatInfo.VelocityY":{"values":["0.00000000"]}},"length":"40","serialized":"00410000000000000000000000000000000000000000000000000000000000000000000000000000"},{"seq":"133","name":"AirThreatInfo_ToComm","id":"65","owner":"ATSManager","date":"20251103","time":"23:32:51.444","elapsed_time":"45303","instance_id":"0","alignment":"false","omt":"false","type":"interaction","operation":"send","data":{"Header.MessageID":{"values":["65"]},"Header.MessageLength":{"values":["0"]},"AirThreatInfo.ObjectID":{"values":["0"]},"AirThreatInfo.ObjectState":{"values":["0"]},"AirThreatInfo.PositionX":{"values":["0.00000000"]},"AirThreatInfo.PositionY":{"values":["0.00000000"]},"AirThreatInfo.VelocityX":{"values":["0.00000000"]},"AirThreatInfo.VelocityY":{"values":["0.00000000"]}},"length":"40","serialized":"00410000000000000000000000000000000000000000000000000000000000000000000000000000"},{"seq":"134","name":"SimulatorStateToComm","id":"32","owner":"StateManager","date":"20251103","time":"23:32:51.514","elapsed_time":"45373","instance_id":"0","alignment":"false","omt":"false","type":"interaction","operation":"send","data":{"SimulatorID":{"values":["102"]}},"length":"2","serialized":"0066"},{"seq":"135","name":"AirThreatInfo_ToComm","id":"65","owner":"ATSManager","date":"20251103","time":"23:32:51.945","elapsed_time":"45804","instance_id":"0","alignment":"false","omt":"false","type":"interaction","operation":"send","data":{"Header.MessageID":{"values":["65"]},"Header.MessageLength":{"values":["0"]},"AirThreatInfo.ObjectID":{"values":["0"]},"AirThreatInfo.ObjectState":{"values":["0"]},"AirThreatInfo.PositionX":{"values":["0.00000000"]},"AirThreatInfo.PositionY":{"values":["0.00000000"]},"AirThreatInfo.VelocityX":{"values":["0.00000000"]},"AirThreatInfo.VelocityY":{"values":["0.00000000"]}},"length":"40","serialized":"00410000000000000000000000000000000000000000000000000000000000000000000000000000"},{"seq":"136","name":"AirThreatInfo_ToComm","id":"65","owner":"ATSManager","date":"20251103","time":"23:32:52.445","elapsed_time":"46304","instance_id":"0","alignment":"false","omt":"false","type":"interaction","operation":"send","data":{"Header.MessageID":{"values":["65"]},"Header.MessageLength":{"values":["0"]},"AirThreatInfo.ObjectID":{"values":["0"]},"AirThreatInfo.ObjectState":{"values":["0"]},"AirThreatInfo.PositionX":{"values":["0.00000000"]},"AirThreatInfo.PositionY":{"values":["0.00000000"]},"AirThreatInfo.VelocityX":{"values":["0.00000000"]},"AirThreatInfo.VelocityY":{"values":["0.00000000"]}},"length":"40","serialized":"00410000000000000000000000000000000000000000000000000000000000000000000000000000"},{"seq":"137","name":"SimulatorStateToComm","id":"32","owner":"StateManager","date":"20251103","time":"23:32:52.514","elapsed_time":"46373","instance_id":"0","alignment":"false","omt":"false","type":"interaction","operation":"send","data":{"SimulatorID":{"values":["102"]}},"length":"2","serialized":"0066"},{"seq":"138","name":"AirThreatInfo_ToComm","id":"65","owner":"ATSManager","date":"20251103","time":"23:32:52.946","elapsed_time":"46805","instance_id":"0","alignment":"false","omt":"false","type":"interaction","operation":"send","data":{"Header.MessageID":{"values":["65"]},"Header.MessageLength":{"values":["0"]},"AirThreatInfo.ObjectID":{"values":["0"]},"AirThreatInfo.ObjectState":{"values":["0"]},"AirThreatInfo.PositionX":{"values":["0.00000000"]},"AirThreatInfo.PositionY":{"values":["0.00000000"]},"AirThreatInfo.VelocityX":{"values":["0.00000000"]},"AirThreatInfo.VelocityY":{"values":["0.00000000"]}},"length":"40","serialized":"00410000000000000000000000000000000000000000000000000000000000000000000000000000"},{"seq":"139","name":"AirThreatInfo_ToComm","id":"65","owner":"ATSManager","date":"20251103","time":"23:32:53.446","elapsed_time":"47305","instance_id":"0","alignment":"false","omt":"false","type":"interaction","operation":"send","data":{"Header.MessageID":{"values":["65"]},"Header.MessageLength":{"values":["0"]},"AirThreatInfo.ObjectID":{"values":["0"]},"AirThreatInfo.ObjectState":{"values":["0"]},"AirThreatInfo.PositionX":{"values":["0.00000000"]},"AirThreatInfo.PositionY":{"values":["0.00000000"]},"AirThreatInfo.VelocityX":{"values":["0.00000000"]},"AirThreatInfo.VelocityY":{"values":["0.00000000"]}},"length":"40","serialized":"00410000000000000000000000000000000000000000000000000000000000000000000000000000"},{"seq":"140","name":"SimulatorStateToComm","id":"32","owner":"StateManager","date":"20251103","time":"23:32:53.513","elapsed_time":"47372","instance_id":"0","alignment":"false","omt":"false","type":"interaction","operation":"send","data":{"SimulatorID":{"values":["102"]}},"length":"2","serialized":"0066"},{"seq":"141","name":"AirThreatInfo_ToComm","id":"65","owner":"ATSManager","date":"20251103","time":"23:32:53.945","elapsed_time":"47804","instance_id":"0","alignment":"false","omt":"false","type":"interaction","operation":"send","data":{"Header.MessageID":{"values":["65"]},"Header.MessageLength":{"values":["0"]},"AirThreatInfo.ObjectID":{"values":["0"]},"AirThreatInfo.ObjectState":{"values":["0"]},"AirThreatInfo.PositionX":{"values":["0.00000000"]},"AirThreatInfo.PositionY":{"values":["0.00000000"]},"AirThreatInfo.VelocityX":{"values":["0.00000000"]},"AirThreatInfo.VelocityY":{"values":["0.00000000"]}},"length":"40","serialized":"00410000000000000000000000000000000000000000000000000000000000000000000000000000"},{"seq":"142","name":"AirThreatInfo_ToComm","id":"65","owner":"ATSManager","date":"20251103","time":"23:32:54.445","elapsed_time":"48304","instance_id":"0","alignment":"false","omt":"false","type":"interaction","operation":"send","data":{"Header.MessageID":{"values":["65"]},"Header.MessageLength":{"values":["0"]},"AirThreatInfo.ObjectID":{"values":["0"]},"AirThreatInfo.ObjectState":{"values":["0"]},"AirThreatInfo.PositionX":{"values":["0.00000000"]},"AirThreatInfo.PositionY":{"values":["0.00000000"]},"AirThreatInfo.VelocityX":{"values":["0.00000000"]},"AirThreatInfo.VelocityY":{"values":["0.00000000"]}},"length":"40","serialized":"00410000000000000000000000000000000000000000000000000000000000000000000000000000"},{"seq":"143","name":"SimulatorStateToComm","id":"32","owner":"StateManager","date":"20251103","time":"23:32:54.514","elapsed_time":"48373","instance_id":"0","alignment":"false","omt":"false","type":"interaction","operation":"send","data":{"SimulatorID":{"values":["102"]}},"length":"2","serialized":"0066"},{"seq":"144","name":"AirThreatInfo_ToComm","id":"65","owner":"ATSManager","date":"20251103","time":"23:32:54.945","elapsed_time":"48804","instance_id":"0","alignment":"false","omt":"false","type":"interaction","operation":"send","data":{"Header.MessageID":{"values":["65"]},"Header.MessageLength":{"values":["0"]},"AirThreatInfo.ObjectID":{"values":["0"]},"AirThreatInfo.ObjectState":{"values":["0"]},"AirThreatInfo.PositionX":{"values":["0.00000000"]},"AirThreatInfo.PositionY":{"values":["0.00000000"]},"AirThreatInfo.VelocityX":{"values":["0.00000000"]},"AirThreatInfo.VelocityY":{"values":["0.00000000"]}},"length":"40","serialized":"00410000000000000000000000000000000000000000000000000000000000000000000000000000"}