[{"seq":"0","name":"SimulatorStateToComm","id":"32","uuid":"13981732355419458428","owner":"StateManager","date":"20260618","time":"21:06:08.441","elapsed_time":"1795","instance_id":"0","alignment":"false","omt":"false","type":"interaction","operation":"send","data":{"SimulatorID":{"values":["102"]}},"length":"2","serialized":"0066"},{"seq":"1","name":"SimulatorStateToComm","id":"32","uuid":"17762686917632466918","owner":"StateManager","date":"20260618","time":"21:06:09.441","elapsed_time":"2795","instance_id":"0","alignment":"false","omt":"false","type":"interaction","operation":"send","data":{"SimulatorID":{"values":["102"]}},"length":"2","serialized":"0066"},{"seq":"2","name":"SimulatorStateToComm","id":"32","uuid":"6038212440664288110","owner":"StateManager","date":"20260618","time":"21:06:10.441","elapsed_time":"3795","instance_id":"0","alignment":"false","omt":"false","type":"interaction","operation":"send","data":{"SimulatorID":{"values":["102"]}},"length":"2","serialized":"0066"},{"seq":"3","name":"SimulatorStateToComm","id":"32","uuid":"18168085295966892074","owner":"StateManager","date":"20260618","time":"21:06:11.441","elapsed_time":"4795","instance_id":"0","alignment":"false","omt":"false","type":"interaction","operation":"send","data":{"SimulatorID":{"values":["102"]}},"length":"2","serialized":"0066"},{"seq":"4","name":"SimulatorStateToComm","id":"32","uuid":"5426213803939724537","owner":"StateManager","date":"20260618","time":"21:06:12.441","elapsed_time":"5795","instance_id":"0","alignment":"false","omt":"false","type":"interaction","operation":"send","data":{"SimulatorID":{"values":["102"]}},"length":"2","serialized":"0066"},{"seq":"5","name":"SimulatorStateToComm","id":"32","uuid":"15359060877184534830","owner":"StateManager","date":"20260618","time":"21:06:13.442","elapsed_time":"6796","instance_id":"0","alignment":"false","omt":"false","type":"interaction","operation":"send","data":{"SimulatorID":{"values":["102"]}},"length":"2","serialized":"0066"},{"seq":"6","name":"SimulatorStateToComm","id":"32","uuid":"17563828627841218625","owner":"StateManager","date":"20260618","time":"21:06:14.441","elapsed_time":"7795","instance_id":"0","alignment":"false","omt":"false","type":"interaction","operation":"send","data":{"SimulatorID":{"values":["102"]}},"length":"2","serialized":"0066"},{"seq":"7","name":"SimulatorStateToComm","id":"32","uuid":"9083032883909937536","owner":"StateManager","date":"20260618","time":"21:06:15.441","elapsed_time":"8795","instance_id":"0","alignment":"false","omt":"false","type":"interaction","operation":"send","data":{"SimulatorID":{"values":["102"]}},"length":"2","serialized":"0066"},{"seq":"8","name":"SimulatorStateToComm","id":"32","uuid":"16955110160475391358","owner":"StateManager","date":"20260618","time":"21:06:16.441","elapsed_time":"9795","instance_id":"0","alignment":"false","omt":"false","type":"interaction","operation":"send","data":{"SimulatorID":{"values":["102"]}},"length":"2","serialized":"0066"},{"seq":"9","name":"SimulatorStateToComm","id":"32","uuid":"6650879400366647684","owner":"StateManager","date":"20260618","time":"21:06:17.460","elapsed_time":"10814","instance_id":"0","alignment":"false","omt":"false","type":"interaction","operation":"send","data":{"SimulatorID":{"values":["102"]}},"length":"2","serialized":"0066"}]