[{"seq":"0","name":"SimulatorStateToComm","id":"32","uuid":"17191213012267964422","owner":"StateManager","date":"20260618","time":"21:06:48.690","elapsed_time":"1822","instance_id":"0","alignment":"false","omt":"false","type":"interaction","operation":"send","data":{"SimulatorID":{"values":["102"]}},"length":"2","serialized":"0066"},{"seq":"1","name":"SimulatorStateToComm","id":"32","uuid":"15165491870132036764","owner":"StateManager","date":"20260618","time":"21:06:49.690","elapsed_time":"2822","instance_id":"0","alignment":"false","omt":"false","type":"interaction","operation":"send","data":{"SimulatorID":{"values":["102"]}},"length":"2","serialized":"0066"},{"seq":"2","name":"SimulatorStateToComm","id":"32","uuid":"6519390819942686934","owner":"StateManager","date":"20260618","time":"21:06:50.691","elapsed_time":"3823","instance_id":"0","alignment":"false","omt":"false","type":"interaction","operation":"send","data":{"SimulatorID":{"values":["102"]}},"length":"2","serialized":"0066"},{"seq":"3","name":"SimulatorStateToComm","id":"32","uuid":"17522567707642083528","owner":"StateManager","date":"20260618","time":"21:06:51.690","elapsed_time":"4822","instance_id":"0","alignment":"false","omt":"false","type":"interaction","operation":"send","data":{"SimulatorID":{"values":["102"]}},"length":"2","serialized":"0066"},{"seq":"4","name":"SimulatorStateToComm","id":"32","uuid":"12649462265918727132","owner":"StateManager","date":"20260618","time":"21:06:52.691","elapsed_time":"5823","instance_id":"0","alignment":"false","omt":"false","type":"interaction","operation":"send","data":{"SimulatorID":{"values":["102"]}},"length":"2","serialized":"0066"},{"seq":"5","name":"SimulatorStateToComm","id":"32","uuid":"12246023672247271807","owner":"StateManager","date":"20260618","time":"21:06:53.691","elapsed_time":"6823","instance_id":"0","alignment":"false","omt":"false","type":"interaction","operation":"send","data":{"SimulatorID":{"values":["102"]}},"length":"2","serialized":"0066"}