[{"seq":"0","name":"SimulatorStateToComm","id":"32","owner":"StateManager","date":"20251104","time":"20:41:18.848","elapsed_time":"1190","instance_id":"0","alignment":"false","omt":"false","type":"interaction","operation":"send","data":{"SimulatorID":{"values":["102"]}},"length":"2","serialized":"0066"},{"seq":"1","name":"SimulatorStateToComm","id":"32","owner":"StateManager","date":"20251104","time":"20:41:19.848","elapsed_time":"2190","instance_id":"0","alignment":"false","omt":"false","type":"interaction","operation":"send","data":{"SimulatorID":{"values":["102"]}},"length":"2","serialized":"0066"},{"seq":"2","name":"SimulatorStateToComm","id":"32","owner":"StateManager","date":"20251104","time":"20:41:20.848","elapsed_time":"3190","instance_id":"0","alignment":"false","omt":"false","type":"interaction","operation":"send","data":{"SimulatorID":{"values":["102"]}},"length":"2","serialized":"0066"},{"seq":"3","name":"SimulatorStateToComm","id":"32","owner":"StateManager","date":"20251104","time":"20:41:21.848","elapsed_time":"4190","instance_id":"0","alignment":"false","omt":"false","type":"interaction","operation":"send","data":{"SimulatorID":{"values":["102"]}},"length":"2","serialized":"0066"},{"seq":"4","name":"SimulatorStateToComm","id":"32","owner":"StateManager","date":"20251104","time":"20:41:22.848","elapsed_time":"5190","instance_id":"0","alignment":"false","omt":"false","type":"interaction","operation":"send","data":{"SimulatorID":{"values":["102"]}},"length":"2","serialized":"0066"},{"seq":"5","name":"SimulatorStateToComm","id":"32","owner":"StateManager","date":"20251104","time":"20:41:23.848","elapsed_time":"6190","instance_id":"0","alignment":"false","omt":"false","type":"interaction","operation":"send","data":{"SimulatorID":{"values":["102"]}},"length":"2","serialized":"0066"},{"seq":"6","name":"SimulatorStateToComm","id":"32","owner":"StateManager","date":"20251104","time":"20:41:24.848","elapsed_time":"7190","instance_id":"0","alignment":"false","omt":"false","type":"interaction","operation":"send","data":{"SimulatorID":{"values":["102"]}},"length":"2","serialized":"0066"},{"seq":"7","name":"SimulatorStateToComm","id":"32","owner":"StateManager","date":"20251104","time":"20:41:25.848","elapsed_time":"8190","instance_id":"0","alignment":"false","omt":"false","type":"interaction","operation":"send","data":{"SimulatorID":{"values":["102"]}},"length":"2","serialized":"0066"},{"seq":"8","name":"SimulatorStateToComm","id":"32","owner":"StateManager","date":"20251104","time":"20:41:26.848","elapsed_time":"9190","instance_id":"0","alignment":"false","omt":"false","type":"interaction","operation":"send","data":{"SimulatorID":{"values":["102"]}},"length":"2","serialized":"0066"},{"seq":"9","name":"SimulatorStateToComm","id":"32","owner":"StateManager","date":"20251104","time":"20:41:27.848","elapsed_time":"10190","instance_id":"0","alignment":"false","omt":"false","type":"interaction","operation":"send","data":{"SimulatorID":{"values":["102"]}},"length":"2","serialized":"0066"},{"seq":"10","name":"SimulatorStateToComm","id":"32","owner":"StateManager","date":"20251104","time":"20:41:28.849","elapsed_time":"11191","instance_id":"0","alignment":"false","omt":"false","type":"interaction","operation":"send","data":{"SimulatorID":{"values":["102"]}},"length":"2","serialized":"0066"},{"seq":"11","name":"SimulatorStateToComm","id":"32","owner":"StateManager","date":"20251104","time":"20:41:29.848","elapsed_time":"12190","instance_id":"0","alignment":"false","omt":"false","type":"interaction","operation":"send","data":{"SimulatorID":{"values":["102"]}},"length":"2","serialized":"0066"},{"seq":"12","name":"SimulatorStateToComm","id":"32","owner":"StateManager","date":"20251104","time":"20:41:30.848","elapsed_time":"13190","instance_id":"0","alignment":"false","omt":"false","type":"interaction","operation":"send","data":{"SimulatorID":{"values":["102"]}},"length":"2","serialized":"0066"},{"seq":"13","name":"SimulatorStateToComm","id":"32","owner":"StateManager","date":"20251104","time":"20:41:31.848","elapsed_time":"14190","instance_id":"0","alignment":"false","omt":"false","type":"interaction","operation":"send","data":{"SimulatorID":{"values":["102"]}},"length":"2","serialized":"0066"},{"seq":"14","name":"SimulatorStateToComm","id":"32","owner":"StateManager","date":"20251104","time":"20:41:32.848","elapsed_time":"15190","instance_id":"0","alignment":"false","omt":"false","type":"interaction","operation":"send","data":{"SimulatorID":{"values":["102"]}},"length":"2","serialized":"0066"},{"seq":"15","name":"SimulatorStateToComm","id":"32","owner":"StateManager","date":"20251104","time":"20:41:33.848","elapsed_time":"16190","instance_id":"0","alignment":"false","omt":"false","type":"interaction","operation":"send","data":{"SimulatorID":{"values":["102"]}},"length":"2","serialized":"0066"},{"seq":"16","name":"SimulatorStateToComm","id":"32","owner":"StateManager","date":"20251104","time":"20:41:34.848","elapsed_time":"17190","instance_id":"0","alignment":"false","omt":"false","type":"interaction","operation":"send","data":{"SimulatorID":{"values":["102"]}},"length":"2","serialized":"0066"},{"seq":"17","name":"SimulatorStateToComm","id":"32","owner":"StateManager","date":"20251104","time":"20:41:35.848","elapsed_time":"18190","instance_id":"0","alignment":"false","omt":"false","type":"interaction","operation":"send","data":{"SimulatorID":{"values":["102"]}},"length":"2","serialized":"0066"},{"seq":"18","name":"SimulatorStateToComm","id":"32","owner":"StateManager","date":"20251104","time":"20:41:36.848","elapsed_time":"19190","instance_id":"0","alignment":"false","omt":"false","type":"interaction","operation":"send","data":{"SimulatorID":{"values":["102"]}},"length":"2","serialized":"0066"},{"seq":"19","name":"SimulatorStateToComm","id":"32","owner":"StateManager","date":"20251104","time":"20:41:37.849","elapsed_time":"20191","instance_id":"0","alignment":"false","omt":"false","type":"interaction","operation":"send","data":{"SimulatorID":{"values":["102"]}},"length":"2","serialized":"0066"},{"seq":"20","name":"SimulatorStateToComm","id":"32","owner":"StateManager","date":"20251104","time":"20:41:38.848","elapsed_time":"21190","instance_id":"0","alignment":"false","omt":"false","type":"interaction","operation":"send","data":{"SimulatorID":{"values":["102"]}},"length":"2","serialized":"0066"},{"seq":"21","name":"SimulatorStateToComm","id":"32","owner":"StateManager","date":"20251104","time":"20:41:39.848","elapsed_time":"22190","instance_id":"0","alignment":"false","omt":"false","type":"interaction","operation":"send","data":{"SimulatorID":{"values":["102"]}},"length":"2","serialized":"0066"},{"seq":"22","name":"SimulatorStateToComm","id":"32","owner":"StateManager","date":"20251104","time":"20:41:40.849","elapsed_time":"23191","instance_id":"0","alignment":"false","omt":"false","type":"interaction","operation":"send","data":{"SimulatorID":{"values":["102"]}},"length":"2","serialized":"0066"},{"seq":"23","name":"SimulatorStateToComm","id":"32","owner":"StateManager","date":"20251104","time":"20:41:41.848","elapsed_time":"24190","instance_id":"0","alignment":"false","omt":"false","type":"interaction","operation":"send","data":{"SimulatorID":{"values":["102"]}},"length":"2","serialized":"0066"},{"seq":"24","name":"SimulatorStateToComm","id":"32","owner":"StateManager","date":"20251104","time":"20:41:42.848","elapsed_time":"25190","instance_id":"0","alignment":"false","omt":"false","type":"interaction","operation":"send","data":{"SimulatorID":{"values":["102"]}},"length":"2","serialized":"0066"},{"seq":"25","name":"SimulatorStateToComm","id":"32","owner":"StateManager","date":"20251104","time":"20:41:43.849","elapsed_time":"26191","instance_id":"0","alignment":"false","omt":"false","type":"interaction","operation":"send","data":{"SimulatorID":{"values":["102"]}},"length":"2","serialized":"0066"},{"seq":"26","name":"SimulatorStateToComm","id":"32","owner":"StateManager","date":"20251104","time":"20:41:44.848","elapsed_time":"27190","instance_id":"0","alignment":"false","omt":"false","type":"interaction","operation":"send","data":{"SimulatorID":{"values":["102"]}},"length":"2","serialized":"0066"},{"seq":"27","name":"SimulatorStateToComm","id":"32","owner":"StateManager","date":"20251104","time":"20:41:45.848","elapsed_time":"28190","instance_id":"0","alignment":"false","omt":"false","type":"interaction","operation":"send","data":{"SimulatorID":{"values":["102"]}},"length":"2","serialized":"0066"},{"seq":"28","name":"SimulatorStateToComm","id":"32","owner":"StateManager","date":"20251104","time":"20:41:46.849","elapsed_time":"29191","instance_id":"0","alignment":"false","omt":"false","type":"interaction","operation":"send","data":{"SimulatorID":{"values":["102"]}},"length":"2","serialized":"0066"},{"seq":"29","name":"SimulatorStateToComm","id":"32","owner":"StateManager","date":"20251104","time":"20:41:47.848","elapsed_time":"30190","instance_id":"0","alignment":"false","omt":"false","type":"interaction","operation":"send","data":{"SimulatorID":{"values":["102"]}},"length":"2","serialized":"0066"},{"seq":"30","name":"SimulatorStateToComm","id":"32","owner":"StateManager","date":"20251104","time":"20:41:48.848","elapsed_time":"31190","instance_id":"0","alignment":"false","omt":"false","type":"interaction","operation":"send","data":{"SimulatorID":{"values":["102"]}},"length":"2","serialized":"0066"},{"seq":"31","name":"SimulatorStateToComm","id":"32","owner":"StateManager","date":"20251104","time":"20:41:49.848","elapsed_time":"32190","instance_id":"0","alignment":"false","omt":"false","type":"interaction","operation":"send","data":{"SimulatorID":{"values":["102"]}},"length":"2","serialized":"0066"},{"seq":"32","name":"SimulatorStateToComm","id":"32","owner":"StateManager","date":"20251104","time":"20:41:50.848","elapsed_time":"33190","instance_id":"0","alignment":"false","omt":"false","type":"interaction","operation":"send","data":{"SimulatorID":{"values":["102"]}},"length":"2","serialized":"0066"},{"seq":"33","name":"SimulatorStateToComm","id":"32","owner":"StateManager","date":"20251104","time":"20:41:51.849","elapsed_time":"34191","instance_id":"0","alignment":"false","omt":"false","type":"interaction","operation":"send","data":{"SimulatorID":{"values":["102"]}},"length":"2","serialized":"0066"},{"seq":"34","name":"SimulatorStateToComm","id":"32","owner":"StateManager","date":"20251104","time":"20:41:52.848","elapsed_time":"35190","instance_id":"0","alignment":"false","omt":"false","type":"interaction","operation":"send","data":{"SimulatorID":{"values":["102"]}},"length":"2","serialized":"0066"},{"seq":"35","name":"SimulatorStateToComm","id":"32","owner":"StateManager","date":"20251104","time":"20:41:53.848","elapsed_time":"36190","instance_id":"0","alignment":"false","omt":"false","type":"interaction","operation":"send","data":{"SimulatorID":{"values":["102"]}},"length":"2","serialized":"0066"}