[{"seq":"0","name":"SimulatorState","id":"11","uuid":"10709957980734560592","owner":"UDPCommunicationManager","date":"20260619","time":"09:43:08.215","elapsed_time":"107271","instance_id":"0","alignment":"false","omt":"false","type":"interaction","operation":"send","semantics":"ATS simulator state","data":{"Header.MessageID":{"values":["11"]},"Header.MessageLength":{"values":["0"]},"SimulatorID":{"values":["102"]}},"length":"6","serialized":"000b00000066"},{"seq":"1","name":"SimulatorState","id":"11","uuid":"16218128331332426659","owner":"UDPCommunicationManager","date":"20260619","time":"09:43:09.211","elapsed_time":"108267","instance_id":"0","alignment":"false","omt":"false","type":"interaction","operation":"send","semantics":"ATS simulator state","data":{"Header.MessageID":{"values":["11"]},"Header.MessageLength":{"values":["0"]},"SimulatorID":{"values":["102"]}},"length":"6","serialized":"000b00000066"},{"seq":"2","name":"SimulatorState","id":"11","uuid":"2689528245976151417","owner":"UDPCommunicationManager","date":"20260619","time":"09:43:10.210","elapsed_time":"109266","instance_id":"0","alignment":"false","omt":"false","type":"interaction","operation":"send","semantics":"ATS simulator state","data":{"Header.MessageID":{"values":["11"]},"Header.MessageLength":{"values":["0"]},"SimulatorID":{"values":["102"]}},"length":"6","serialized":"000b00000066"},{"seq":"3","name":"SimulatorState","id":"11","uuid":"11193522932716148732","owner":"UDPCommunicationManager","date":"20260619","time":"09:43:11.209","elapsed_time":"110265","instance_id":"0","alignment":"false","omt":"false","type":"interaction","operation":"send","semantics":"ATS simulator state","data":{"Header.MessageID":{"values":["11"]},"Header.MessageLength":{"values":["0"]},"SimulatorID":{"values":["102"]}},"length":"6","serialized":"000b00000066"},{"seq":"4","name":"SimulatorState","id":"11","uuid":"2599021048295397930","owner":"UDPCommunicationManager","date":"20260619","time":"09:43:12.211","elapsed_time":"111267","instance_id":"0","alignment":"false","omt":"false","type":"interaction","operation":"send","semantics":"ATS simulator state","data":{"Header.MessageID":{"values":["11"]},"Header.MessageLength":{"values":["0"]},"SimulatorID":{"values":["102"]}},"length":"6","serialized":"000b00000066"},{"seq":"5","name":"SimulatorState","id":"11","uuid":"13545285209631478524","owner":"UDPCommunicationManager","date":"20260619","time":"09:43:31.675","elapsed_time":"130731","instance_id":"0","alignment":"false","omt":"false","type":"interaction","operation":"send","semantics":"ATS simulator state","data":{"Header.MessageID":{"values":["11"]},"Header.MessageLength":{"values":["0"]},"SimulatorID":{"values":["102"]}},"length":"6","serialized":"000b00000066"},{"seq":"6","name":"SimulatorState","id":"11","uuid":"17388998346455406843","owner":"UDPCommunicationManager","date":"20260619","time":"09:43:32.675","elapsed_time":"131731","instance_id":"0","alignment":"false","omt":"false","type":"interaction","operation":"send","semantics":"ATS simulator state","data":{"Header.MessageID":{"values":["11"]},"Header.MessageLength":{"values":["0"]},"SimulatorID":{"values":["102"]}},"length":"6","serialized":"000b00000066"},{"seq":"7","name":"SimulatorState","id":"11","uuid":"12630995688093021020","owner":"UDPCommunicationManager","date":"20260619","time":"09:43:33.675","elapsed_time":"132731","instance_id":"0","alignment":"false","omt":"false","type":"interaction","operation":"send","semantics":"ATS simulator state","data":{"Header.MessageID":{"values":["11"]},"Header.MessageLength":{"values":["0"]},"SimulatorID":{"values":["102"]}},"length":"6","serialized":"000b00000066"},{"seq":"8","name":"SimulatorState","id":"11","uuid":"11721375861664839507","owner":"UDPCommunicationManager","date":"20260619","time":"09:43:34.675","elapsed_time":"133731","instance_id":"0","alignment":"false","omt":"false","type":"interaction","operation":"send","semantics":"ATS simulator state","data":{"Header.MessageID":{"values":["11"]},"Header.MessageLength":{"values":["0"]},"SimulatorID":{"values":["102"]}},"length":"6","serialized":"000b00000066"},{"seq":"9","name":"SimulatorState","id":"11","uuid":"743106938787320090","owner":"UDPCommunicationManager","date":"20260619","time":"09:43:35.675","elapsed_time":"134731","instance_id":"0","alignment":"false","omt":"false","type":"interaction","operation":"send","semantics":"ATS simulator state","data":{"Header.MessageID":{"values":["11"]},"Header.MessageLength":{"values":["0"]},"SimulatorID":{"values":["102"]}},"length":"6","serialized":"000b00000066"},{"seq":"10","name":"SimulatorState","id":"11","uuid":"11540968138557098539","owner":"UDPCommunicationManager","date":"20260619","time":"09:43:36.676","elapsed_time":"135732","instance_id":"0","alignment":"false","omt":"false","type":"interaction","operation":"send","semantics":"ATS simulator state","data":{"Header.MessageID":{"values":["11"]},"Header.MessageLength":{"values":["0"]},"SimulatorID":{"values":["102"]}},"length":"6","serialized":"000b00000066"},{"seq":"11","name":"SimulatorState","id":"11","uuid":"5689033258946828536","owner":"UDPCommunicationManager","date":"20260619","time":"09:43:37.675","elapsed_time":"136731","instance_id":"0","alignment":"false","omt":"false","type":"interaction","operation":"send","semantics":"ATS simulator state","data":{"Header.MessageID":{"values":["11"]},"Header.MessageLength":{"values":["0"]},"SimulatorID":{"values":["102"]}},"length":"6","serialized":"000b00000066"},{"seq":"12","name":"SimulatorState","id":"11","uuid":"7897172012393629250","owner":"UDPCommunicationManager","date":"20260619","time":"09:43:38.675","elapsed_time":"137731","instance_id":"0","alignment":"false","omt":"false","type":"interaction","operation":"send","semantics":"ATS simulator state","data":{"Header.MessageID":{"values":["11"]},"Header.MessageLength":{"values":["0"]},"SimulatorID":{"values":["102"]}},"length":"6","serialized":"000b00000066"},{"seq":"13","name":"SimulatorState","id":"11","uuid":"16312341890742342946","owner":"UDPCommunicationManager","date":"20260619","time":"09:43:39.676","elapsed_time":"138732","instance_id":"0","alignment":"false","omt":"false","type":"interaction","operation":"send","semantics":"ATS simulator state","data":{"Header.MessageID":{"values":["11"]},"Header.MessageLength":{"values":["0"]},"SimulatorID":{"values":["102"]}},"length":"6","serialized":"000b00000066"},{"seq":"14","name":"SimulatorState","id":"11","uuid":"5733951032345996214","owner":"UDPCommunicationManager","date":"20260619","time":"09:43:40.675","elapsed_time":"139731","instance_id":"0","alignment":"false","omt":"false","type":"interaction","operation":"send","semantics":"ATS simulator state","data":{"Header.MessageID":{"values":["11"]},"Header.MessageLength":{"values":["0"]},"SimulatorID":{"values":["102"]}},"length":"6","serialized":"000b00000066"},{"seq":"15","name":"SimulatorState","id":"11","uuid":"16725611039886323449","owner":"UDPCommunicationManager","date":"20260619","time":"09:43:41.676","elapsed_time":"140732","instance_id":"0","alignment":"false","omt":"false","type":"interaction","operation":"send","semantics":"ATS simulator state","data":{"Header.MessageID":{"values":["11"]},"Header.MessageLength":{"values":["0"]},"SimulatorID":{"values":["102"]}},"length":"6","serialized":"000b00000066"},{"seq":"16","name":"SimulatorState","id":"11","uuid":"14793631180026095679","owner":"UDPCommunicationManager","date":"20260619","time":"09:43:42.676","elapsed_time":"141732","instance_id":"0","alignment":"false","omt":"false","type":"interaction","operation":"send","semantics":"ATS simulator state","data":{"Header.MessageID":{"values":["11"]},"Header.MessageLength":{"values":["0"]},"SimulatorID":{"values":["102"]}},"length":"6","serialized":"000b00000066"},{"seq":"17","name":"SimulatorState","id":"11","uuid":"13277704218712176687","owner":"UDPCommunicationManager","date":"20260619","time":"09:43:43.675","elapsed_time":"142731","instance_id":"0","alignment":"false","omt":"false","type":"interaction","operation":"send","semantics":"ATS simulator state","data":{"Header.MessageID":{"values":["11"]},"Header.MessageLength":{"values":["0"]},"SimulatorID":{"values":["102"]}},"length":"6","serialized":"000b00000066"},{"seq":"18","name":"SimulatorState","id":"11","uuid":"4015141393350002444","owner":"UDPCommunicationManager","date":"20260619","time":"09:43:44.675","elapsed_time":"143731","instance_id":"0","alignment":"false","omt":"false","type":"interaction","operation":"send","semantics":"ATS simulator state","data":{"Header.MessageID":{"values":["11"]},"Header.MessageLength":{"values":["0"]},"SimulatorID":{"values":["102"]}},"length":"6","serialized":"000b00000066"},{"seq":"19","name":"SimulatorState","id":"11","uuid":"10649713203372072248","owner":"UDPCommunicationManager","date":"20260619","time":"09:43:45.674","elapsed_time":"144730","instance_id":"0","alignment":"false","omt":"false","type":"interaction","operation":"send","semantics":"ATS simulator state","data":{"Header.MessageID":{"values":["11"]},"Header.MessageLength":{"values":["0"]},"SimulatorID":{"values":["102"]}},"length":"6","serialized":"000b00000066"},{"seq":"20","name":"SimulatorState","id":"11","uuid":"17834392388299367091","owner":"UDPCommunicationManager","date":"20260619","time":"09:43:46.676","elapsed_time":"145732","instance_id":"0","alignment":"false","omt":"false","type":"interaction","operation":"send","semantics":"ATS simulator state","data":{"Header.MessageID":{"values":["11"]},"Header.MessageLength":{"values":["0"]},"SimulatorID":{"values":["102"]}},"length":"6","serialized":"000b00000066"},{"seq":"21","name":"SimulatorState","id":"11","uuid":"6805736484885647024","owner":"UDPCommunicationManager","date":"20260619","time":"09:43:47.674","elapsed_time":"146730","instance_id":"0","alignment":"false","omt":"false","type":"interaction","operation":"send","semantics":"ATS simulator state","data":{"Header.MessageID":{"values":["11"]},"Header.MessageLength":{"values":["0"]},"SimulatorID":{"values":["102"]}},"length":"6","serialized":"000b00000066"},{"seq":"22","name":"SimulatorState","id":"11","uuid":"17173205010886656645","owner":"UDPCommunicationManager","date":"20260619","time":"09:43:48.676","elapsed_time":"147732","instance_id":"0","alignment":"false","omt":"false","type":"interaction","operation":"send","semantics":"ATS simulator state","data":{"Header.MessageID":{"values":["11"]},"Header.MessageLength":{"values":["0"]},"SimulatorID":{"values":["102"]}},"length":"6","serialized":"000b00000066"},{"seq":"23","name":"SimulatorState","id":"11","uuid":"3033720047680196664","owner":"UDPCommunicationManager","date":"20260619","time":"09:43:49.675","elapsed_time":"148731","instance_id":"0","alignment":"false","omt":"false","type":"interaction","operation":"send","semantics":"ATS simulator state","data":{"Header.MessageID":{"values":["11"]},"Header.MessageLength":{"values":["0"]},"SimulatorID":{"values":["102"]}},"length":"6","serialized":"000b00000066"},{"seq":"24","name":"SimulatorState","id":"11","uuid":"13891375219776785319","owner":"UDPCommunicationManager","date":"20260619","time":"09:43:50.674","elapsed_time":"149730","instance_id":"0","alignment":"false","omt":"false","type":"interaction","operation":"send","semantics":"ATS simulator state","data":{"Header.MessageID":{"values":["11"]},"Header.MessageLength":{"values":["0"]},"SimulatorID":{"values":["102"]}},"length":"6","serialized":"000b00000066"},{"seq":"25","name":"SimulatorState","id":"11","uuid":"7782832634394531904","owner":"UDPCommunicationManager","date":"20260619","time":"09:43:51.676","elapsed_time":"150732","instance_id":"0","alignment":"false","omt":"false","type":"interaction","operation":"send","semantics":"ATS simulator state","data":{"Header.MessageID":{"values":["11"]},"Header.MessageLength":{"values":["0"]},"SimulatorID":{"values":["102"]}},"length":"6","serialized":"000b00000066"},{"seq":"26","name":"SimulatorState","id":"11","uuid":"9771479805368683960","owner":"UDPCommunicationManager","date":"20260619","time":"09:43:52.674","elapsed_time":"151730","instance_id":"0","alignment":"false","omt":"false","type":"interaction","operation":"send","semantics":"ATS simulator state","data":{"Header.MessageID":{"values":["11"]},"Header.MessageLength":{"values":["0"]},"SimulatorID":{"values":["102"]}},"length":"6","serialized":"000b00000066"},{"seq":"27","name":"SimulatorState","id":"11","uuid":"16165235910918565307","owner":"UDPCommunicationManager","date":"20260619","time":"09:43:53.675","elapsed_time":"152731","instance_id":"0","alignment":"false","omt":"false","type":"interaction","operation":"send","semantics":"ATS simulator state","data":{"Header.MessageID":{"values":["11"]},"Header.MessageLength":{"values":["0"]},"SimulatorID":{"values":["102"]}},"length":"6","serialized":"000b00000066"},{"seq":"28","name":"SimulatorState","id":"11","uuid":"14807713497198031946","owner":"UDPCommunicationManager","date":"20260619","time":"09:43:54.676","elapsed_time":"153732","instance_id":"0","alignment":"false","omt":"false","type":"interaction","operation":"send","semantics":"ATS simulator state","data":{"Header.MessageID":{"values":["11"]},"Header.MessageLength":{"values":["0"]},"SimulatorID":{"values":["102"]}},"length":"6","serialized":"000b00000066"},{"seq":"29","name":"SimulatorState","id":"11","uuid":"2931209949244096591","owner":"UDPCommunicationManager","date":"20260619","time":"09:43:55.676","elapsed_time":"154732","instance_id":"0","alignment":"false","omt":"false","type":"interaction","operation":"send","semantics":"ATS simulator state","data":{"Header.MessageID":{"values":["11"]},"Header.MessageLength":{"values":["0"]},"SimulatorID":{"values":["102"]}},"length":"6","serialized":"000b00000066"},{"seq":"30","name":"SimulatorState","id":"11","uuid":"14004134100960924115","owner":"UDPCommunicationManager","date":"20260619","time":"09:43:56.677","elapsed_time":"155733","instance_id":"0","alignment":"false","omt":"false","type":"interaction","operation":"send","semantics":"ATS simulator state","data":{"Header.MessageID":{"values":["11"]},"Header.MessageLength":{"values":["0"]},"SimulatorID":{"values":["102"]}},"length":"6","serialized":"000b00000066"},{"seq":"31","name":"SimulatorState","id":"11","uuid":"6993612804793586121","owner":"UDPCommunicationManager","date":"20260619","time":"09:43:57.677","elapsed_time":"156733","instance_id":"0","alignment":"false","omt":"false","type":"interaction","operation":"send","semantics":"ATS simulator state","data":{"Header.MessageID":{"values":["11"]},"Header.MessageLength":{"values":["0"]},"SimulatorID":{"values":["102"]}},"length":"6","serialized":"000b00000066"},{"seq":"32","name":"SimulatorState","id":"11","uuid":"9060914694222385471","owner":"UDPCommunicationManager","date":"20260619","time":"09:43:58.676","elapsed_time":"157732","instance_id":"0","alignment":"false","omt":"false","type":"interaction","operation":"send","semantics":"ATS simulator state","data":{"Header.MessageID":{"values":["11"]},"Header.MessageLength":{"values":["0"]},"SimulatorID":{"values":["102"]}},"length":"6","serialized":"000b00000066"},{"seq":"33","name":"SimulatorState","id":"11","uuid":"17766958406601708694","owner":"UDPCommunicationManager","date":"20260619","time":"09:43:59.675","elapsed_time":"158731","instance_id":"0","alignment":"false","omt":"false","type":"interaction","operation":"send","semantics":"ATS simulator state","data":{"Header.MessageID":{"values":["11"]},"Header.MessageLength":{"values":["0"]},"SimulatorID":{"values":["102"]}},"length":"6","serialized":"000b00000066"},{"seq":"34","name":"SimulatorState","id":"11","uuid":"4420272415858054066","owner":"UDPCommunicationManager","date":"20260619","time":"09:44:00.676","elapsed_time":"159732","instance_id":"0","alignment":"false","omt":"false","type":"interaction","operation":"send","semantics":"ATS simulator state","data":{"Header.MessageID":{"values":["11"]},"Header.MessageLength":{"values":["0"]},"SimulatorID":{"values":["102"]}},"length":"6","serialized":"000b00000066"},{"seq":"35","name":"SimulatorState","id":"11","uuid":"10694911291878719771","owner":"UDPCommunicationManager","date":"20260619","time":"09:44:01.675","elapsed_time":"160731","instance_id":"0","alignment":"false","omt":"false","type":"interaction","operation":"send","semantics":"ATS simulator state","data":{"Header.MessageID":{"values":["11"]},"Header.MessageLength":{"values":["0"]},"SimulatorID":{"values":["102"]}},"length":"6","serialized":"000b00000066"},{"seq":"36","name":"StartSimulation","id":"6","uuid":"6189947292190320128","owner":"UIManager","date":"20260619","time":"09:44:02.274","elapsed_time":"161330","instance_id":"0","alignment":"false","omt":"false","type":"interaction","operation":"send","semantics":"모의 시작/중지 명령 (OC 송신)","data":{"Header.MessageID":{"values":["6"]},"Header.MessageLength":{"values":["2"]},"simulationStatus":{"values":["true"]}},"length":"5","serialized":"0006000201"},{"seq":"37","name":"SimulatorState","id":"11","uuid":"14417583971988183300","owner":"UDPCommunicationManager","date":"20260619","time":"09:44:02.676","elapsed_time":"161732","instance_id":"0","alignment":"false","omt":"false","type":"interaction","operation":"send","semantics":"ATS simulator state","data":{"Header.MessageID":{"values":["11"]},"Header.MessageLength":{"values":["0"]},"SimulatorID":{"values":["102"]}},"length":"6","serialized":"000b00000066"},{"seq":"38","name":"SimulatorState","id":"11","uuid":"5995878244839579573","owner":"UDPCommunicationManager","date":"20260619","time":"09:44:03.674","elapsed_time":"162730","instance_id":"0","alignment":"false","omt":"false","type":"interaction","operation":"send","semantics":"ATS simulator state","data":{"Header.MessageID":{"values":["11"]},"Header.MessageLength":{"values":["0"]},"SimulatorID":{"values":["102"]}},"length":"6","serialized":"000b00000066"},{"seq":"39","name":"SimulatorState","id":"11","uuid":"2342413801593866742","owner":"UDPCommunicationManager","date":"20260619","time":"09:44:04.674","elapsed_time":"163730","instance_id":"0","alignment":"false","omt":"false","type":"interaction","operation":"send","semantics":"ATS simulator state","data":{"Header.MessageID":{"values":["11"]},"Header.MessageLength":{"values":["0"]},"SimulatorID":{"values":["102"]}},"length":"6","serialized":"000b00000066"},{"seq":"40","name":"SimulatorState","id":"11","uuid":"10144647598782275773","owner":"UDPCommunicationManager","date":"20260619","time":"09:44:05.676","elapsed_time":"164732","instance_id":"0","alignment":"false","omt":"false","type":"interaction","operation":"send","semantics":"ATS simulator state","data":{"Header.MessageID":{"values":["11"]},"Header.MessageLength":{"values":["0"]},"SimulatorID":{"values":["102"]}},"length":"6","serialized":"000b00000066"},{"seq":"41","name":"SimulatorState","id":"11","uuid":"9027482350825037244","owner":"UDPCommunicationManager","date":"20260619","time":"09:44:06.676","elapsed_time":"165732","instance_id":"0","alignment":"false","omt":"false","type":"interaction","operation":"send","semantics":"ATS simulator state","data":{"Header.MessageID":{"values":["11"]},"Header.MessageLength":{"values":["0"]},"SimulatorID":{"values":["102"]}},"length":"6","serialized":"000b00000066"},{"seq":"42","name":"SimulatorState","id":"11","uuid":"3855349588035567217","owner":"UDPCommunicationManager","date":"20260619","time":"09:44:07.675","elapsed_time":"166731","instance_id":"0","alignment":"false","omt":"false","type":"interaction","operation":"send","semantics":"ATS simulator state","data":{"Header.MessageID":{"values":["11"]},"Header.MessageLength":{"values":["0"]},"SimulatorID":{"values":["102"]}},"length":"6","serialized":"000b00000066"},{"seq":"43","name":"SimulatorState","id":"11","uuid":"12501785890510799357","owner":"UDPCommunicationManager","date":"20260619","time":"09:44:08.676","elapsed_time":"167732","instance_id":"0","alignment":"false","omt":"false","type":"interaction","operation":"send","semantics":"ATS simulator state","data":{"Header.MessageID":{"values":["11"]},"Header.MessageLength":{"values":["0"]},"SimulatorID":{"values":["102"]}},"length":"6","serialized":"000b00000066"},{"seq":"44","name":"SimulatorState","id":"11","uuid":"6814306329240564467","owner":"UDPCommunicationManager","date":"20260619","time":"09:44:09.676","elapsed_time":"168732","instance_id":"0","alignment":"false","omt":"false","type":"interaction","operation":"send","semantics":"ATS simulator state","data":{"Header.MessageID":{"values":["11"]},"Header.MessageLength":{"values":["0"]},"SimulatorID":{"values":["102"]}},"length":"6","serialized":"000b00000066"},{"seq":"45","name":"SimulatorState","id":"11","uuid":"10757511536844524606","owner":"UDPCommunicationManager","date":"20260619","time":"09:44:10.676","elapsed_time":"169732","instance_id":"0","alignment":"false","omt":"false","type":"interaction","operation":"send","semantics":"ATS simulator state","data":{"Header.MessageID":{"values":["11"]},"Header.MessageLength":{"values":["0"]},"SimulatorID":{"values":["102"]}},"length":"6","serialized":"000b00000066"},{"seq":"46","name":"SimulatorState","id":"11","uuid":"2391704891195285176","owner":"UDPCommunicationManager","date":"20260619","time":"09:44:11.675","elapsed_time":"170731","instance_id":"0","alignment":"false","omt":"false","type":"interaction","operation":"send","semantics":"ATS simulator state","data":{"Header.MessageID":{"values":["11"]},"Header.MessageLength":{"values":["0"]},"SimulatorID":{"values":["102"]}},"length":"6","serialized":"000b00000066"},{"seq":"47","name":"SimulatorState","id":"11","uuid":"16580137177708560767","owner":"UDPCommunicationManager","date":"20260619","time":"09:44:12.676","elapsed_time":"171732","instance_id":"0","alignment":"false","omt":"false","type":"interaction","operation":"send","semantics":"ATS simulator state","data":{"Header.MessageID":{"values":["11"]},"Header.MessageLength":{"values":["0"]},"SimulatorID":{"values":["102"]}},"length":"6","serialized":"000b00000066"},{"seq":"48","name":"SimulatorState","id":"11","uuid":"16530877880003731194","owner":"UDPCommunicationManager","date":"20260619","time":"09:44:13.676","elapsed_time":"172732","instance_id":"0","alignment":"false","omt":"false","type":"interaction","operation":"send","semantics":"ATS simulator state","data":{"Header.MessageID":{"values":["11"]},"Header.MessageLength":{"values":["0"]},"SimulatorID":{"values":["102"]}},"length":"6","serialized":"000b00000066"},{"seq":"49","name":"SimulatorState","id":"11","uuid":"13552574041698851868","owner":"UDPCommunicationManager","date":"20260619","time":"09:44:14.676","elapsed_time":"173732","instance_id":"0","alignment":"false","omt":"false","type":"interaction","operation":"send","semantics":"ATS simulator state","data":{"Header.MessageID":{"values":["11"]},"Header.MessageLength":{"values":["0"]},"SimulatorID":{"values":["102"]}},"length":"6","serialized":"000b00000066"},{"seq":"50","name":"SimulatorState","id":"11","uuid":"11371322950004573662","owner":"UDPCommunicationManager","date":"20260619","time":"09:44:15.676","elapsed_time":"174732","instance_id":"0","alignment":"false","omt":"false","type":"interaction","operation":"send","semantics":"ATS simulator state","data":{"Header.MessageID":{"values":["11"]},"Header.MessageLength":{"values":["0"]},"SimulatorID":{"values":["102"]}},"length":"6","serialized":"000b00000066"},{"seq":"51","name":"SimulatorState","id":"11","uuid":"4211339487541457121","owner":"UDPCommunicationManager","date":"20260619","time":"09:44:16.675","elapsed_time":"175731","instance_id":"0","alignment":"false","omt":"false","type":"interaction","operation":"send","semantics":"ATS simulator state","data":{"Header.MessageID":{"values":["11"]},"Header.MessageLength":{"values":["0"]},"SimulatorID":{"values":["102"]}},"length":"6","serialized":"000b00000066"},{"seq":"52","name":"SimulatorState","id":"11","uuid":"4717537878302303808","owner":"UDPCommunicationManager","date":"20260619","time":"09:44:17.676","elapsed_time":"176732","instance_id":"0","alignment":"false","omt":"false","type":"interaction","operation":"send","semantics":"ATS simulator state","data":{"Header.MessageID":{"values":["11"]},"Header.MessageLength":{"values":["0"]},"SimulatorID":{"values":["102"]}},"length":"6","serialized":"000b00000066"},{"seq":"53","name":"SimulatorState","id":"11","uuid":"12454909725919993465","owner":"UDPCommunicationManager","date":"20260619","time":"09:44:18.675","elapsed_time":"177731","instance_id":"0","alignment":"false","omt":"false","type":"interaction","operation":"send","semantics":"ATS simulator state","data":{"Header.MessageID":{"values":["11"]},"Header.MessageLength":{"values":["0"]},"SimulatorID":{"values":["102"]}},"length":"6","serialized":"000b00000066"},{"seq":"54","name":"SimulatorState","id":"11","uuid":"17416992195649942938","owner":"UDPCommunicationManager","date":"20260619","time":"09:44:19.676","elapsed_time":"178732","instance_id":"0","alignment":"false","omt":"false","type":"interaction","operation":"send","semantics":"ATS simulator state","data":{"Header.MessageID":{"values":["11"]},"Header.MessageLength":{"values":["0"]},"SimulatorID":{"values":["102"]}},"length":"6","serialized":"000b00000066"},{"seq":"55","name":"SimulatorState","id":"11","uuid":"15393720277435695708","owner":"UDPCommunicationManager","date":"20260619","time":"09:44:20.675","elapsed_time":"179731","instance_id":"0","alignment":"false","omt":"false","type":"interaction","operation":"send","semantics":"ATS simulator state","data":{"Header.MessageID":{"values":["11"]},"Header.MessageLength":{"values":["0"]},"SimulatorID":{"values":["102"]}},"length":"6","serialized":"000b00000066"},{"seq":"56","name":"SimulatorState","id":"11","uuid":"2639557247639727105","owner":"UDPCommunicationManager","date":"20260619","time":"09:44:21.676","elapsed_time":"180732","instance_id":"0","alignment":"false","omt":"false","type":"interaction","operation":"send","semantics":"ATS simulator state","data":{"Header.MessageID":{"values":["11"]},"Header.MessageLength":{"values":["0"]},"SimulatorID":{"values":["102"]}},"length":"6","serialized":"000b00000066"},{"seq":"57","name":"SimulatorState","id":"11","uuid":"6652433628761743873","owner":"UDPCommunicationManager","date":"20260619","time":"09:44:22.675","elapsed_time":"181731","instance_id":"0","alignment":"false","omt":"false","type":"interaction","operation":"send","semantics":"ATS simulator state","data":{"Header.MessageID":{"values":["11"]},"Header.MessageLength":{"values":["0"]},"SimulatorID":{"values":["102"]}},"length":"6","serialized":"000b00000066"},{"seq":"58","name":"SimulatorState","id":"11","uuid":"6784053534130617970","owner":"UDPCommunicationManager","date":"20260619","time":"09:44:23.675","elapsed_time":"182731","instance_id":"0","alignment":"false","omt":"false","type":"interaction","operation":"send","semantics":"ATS simulator state","data":{"Header.MessageID":{"values":["11"]},"Header.MessageLength":{"values":["0"]},"SimulatorID":{"values":["102"]}},"length":"6","serialized":"000b00000066"},{"seq":"59","name":"SimulatorState","id":"11","uuid":"3312474583333873976","owner":"UDPCommunicationManager","date":"20260619","time":"09:44:24.676","elapsed_time":"183732","instance_id":"0","alignment":"false","omt":"false","type":"interaction","operation":"send","semantics":"ATS simulator state","data":{"Header.MessageID":{"values":["11"]},"Header.MessageLength":{"values":["0"]},"SimulatorID":{"values":["102"]}},"length":"6","serialized":"000b00000066"},{"seq":"60","name":"SimulatorState","id":"11","uuid":"5796304581606287851","owner":"UDPCommunicationManager","date":"20260619","time":"09:44:25.676","elapsed_time":"184732","instance_id":"0","alignment":"false","omt":"false","type":"interaction","operation":"send","semantics":"ATS simulator state","data":{"Header.MessageID":{"values":["11"]},"Header.MessageLength":{"values":["0"]},"SimulatorID":{"values":["102"]}},"length":"6","serialized":"000b00000066"},{"seq":"61","name":"SimulatorState","id":"11","uuid":"16300846056086102264","owner":"UDPCommunicationManager","date":"20260619","time":"09:44:26.676","elapsed_time":"185732","instance_id":"0","alignment":"false","omt":"false","type":"interaction","operation":"send","semantics":"ATS simulator state","data":{"Header.MessageID":{"values":["11"]},"Header.MessageLength":{"values":["0"]},"SimulatorID":{"values":["102"]}},"length":"6","serialized":"000b00000066"},{"seq":"62","name":"SimulatorState","id":"11","uuid":"16307070755619700889","owner":"UDPCommunicationManager","date":"20260619","time":"09:44:27.675","elapsed_time":"186731","instance_id":"0","alignment":"false","omt":"false","type":"interaction","operation":"send","semantics":"ATS simulator state","data":{"Header.MessageID":{"values":["11"]},"Header.MessageLength":{"values":["0"]},"SimulatorID":{"values":["102"]}},"length":"6","serialized":"000b00000066"},{"seq":"63","name":"SimulatorState","id":"11","uuid":"11109270388304791363","owner":"UDPCommunicationManager","date":"20260619","time":"09:44:28.674","elapsed_time":"187730","instance_id":"0","alignment":"false","omt":"false","type":"interaction","operation":"send","semantics":"ATS simulator state","data":{"Header.MessageID":{"values":["11"]},"Header.MessageLength":{"values":["0"]},"SimulatorID":{"values":["102"]}},"length":"6","serialized":"000b00000066"},{"seq":"64","name":"SimulatorState","id":"11","uuid":"2954967776263575377","owner":"UDPCommunicationManager","date":"20260619","time":"09:44:29.675","elapsed_time":"188731","instance_id":"0","alignment":"false","omt":"false","type":"interaction","operation":"send","semantics":"ATS simulator state","data":{"Header.MessageID":{"values":["11"]},"Header.MessageLength":{"values":["0"]},"SimulatorID":{"values":["102"]}},"length":"6","serialized":"000b00000066"},{"seq":"65","name":"SimulatorState","id":"11","uuid":"4096952804983871100","owner":"UDPCommunicationManager","date":"20260619","time":"09:44:30.675","elapsed_time":"189731","instance_id":"0","alignment":"false","omt":"false","type":"interaction","operation":"send","semantics":"ATS simulator state","data":{"Header.MessageID":{"values":["11"]},"Header.MessageLength":{"values":["0"]},"SimulatorID":{"values":["102"]}},"length":"6","serialized":"000b00000066"},{"seq":"66","name":"SimulatorState","id":"11","uuid":"17038327123268622267","owner":"UDPCommunicationManager","date":"20260619","time":"09:44:31.677","elapsed_time":"190733","instance_id":"0","alignment":"false","omt":"false","type":"interaction","operation":"send","semantics":"ATS simulator state","data":{"Header.MessageID":{"values":["11"]},"Header.MessageLength":{"values":["0"]},"SimulatorID":{"values":["102"]}},"length":"6","serialized":"000b00000066"},{"seq":"67","name":"Stop","id":"16","uuid":"7286042308086560365","owner":"UIManager","date":"20260619","time":"09:44:32.044","elapsed_time":"191100","instance_id":"0","alignment":"false","omt":"false","type":"interaction","operation":"send","semantics":"모의 중지 명령 (OC 송신)","data":{"Header.MessageID":{"values":["16"]},"Header.MessageLength":{"values":["2"]},"stopFlag":{"values":["true"]}},"length":"5","serialized":"0010000201"},{"seq":"68","name":"SimulatorState","id":"11","uuid":"16178173590308840720","owner":"UDPCommunicationManager","date":"20260619","time":"09:44:32.676","elapsed_time":"191732","instance_id":"0","alignment":"false","omt":"false","type":"interaction","operation":"send","semantics":"ATS simulator state","data":{"Header.MessageID":{"values":["11"]},"Header.MessageLength":{"values":["0"]},"SimulatorID":{"values":["102"]}},"length":"6","serialized":"000b00000066"},{"seq":"69","name":"SimulatorState","id":"11","uuid":"8980931511542436413","owner":"UDPCommunicationManager","date":"20260619","time":"09:44:33.674","elapsed_time":"192730","instance_id":"0","alignment":"false","omt":"false","type":"interaction","operation":"send","semantics":"ATS simulator state","data":{"Header.MessageID":{"values":["11"]},"Header.MessageLength":{"values":["0"]},"SimulatorID":{"values":["102"]}},"length":"6","serialized":"000b00000066"},{"seq":"70","name":"SimulatorState","id":"11","uuid":"14458738723280685374","owner":"UDPCommunicationManager","date":"20260619","time":"09:44:34.675","elapsed_time":"193731","instance_id":"0","alignment":"false","omt":"false","type":"interaction","operation":"send","semantics":"ATS simulator state","data":{"Header.MessageID":{"values":["11"]},"Header.MessageLength":{"values":["0"]},"SimulatorID":{"values":["102"]}},"length":"6","serialized":"000b00000066"},{"seq":"71","name":"SimulatorState","id":"11","uuid":"6469934006758983853","owner":"UDPCommunicationManager","date":"20260619","time":"09:44:35.675","elapsed_time":"194731","instance_id":"0","alignment":"false","omt":"false","type":"interaction","operation":"send","semantics":"ATS simulator state","data":{"Header.MessageID":{"values":["11"]},"Header.MessageLength":{"values":["0"]},"SimulatorID":{"values":["102"]}},"length":"6","serialized":"000b00000066"}]